Workbook
Name Adj_Market_Cap: [9]MASK!$B$18
Name COLUMN_CURR_YEAR: [9]MASK!$EV$10
Name COLUMN_FISCAL_YEAR: [9]MASK!$EV$16
Name COLUMN_LAST_QUARTER: [9]MASK!$EV$11
Name Curr_EV: [9]MASK!$B$22
Name Curr_MCap: [9]MASK!$B$17
Name Current_Year: [9]MASK!$EV$9
Name Data: #REF!
Name Dvd_Paid: [9]MASK!$D$15
Name Ext_DVD_Short_Term: [9]MASK!$B$19
Name Fair_Eq_Tdy_KeHigh: [9]MASK!$B$466
Name Fair_Eq_Tdy_KeLow: [9]MASK!$B$463
Name Fiscal_Month: [9]MASK!$EV$15
Name Fiscal_Year: [9]MASK!$EV$8
Name G_Perp_Nominal: [9]MASK!$B$27
Name G_Perp_Real: [9]MASK!$B$25
Name Hoje: [9]MASK!$EV$13
Name Ke_High: [9]MASK!$B$29
Name Ke_Low: [9]MASK!$B$28
Name LAST_QUARTER: [9]MASK!$B$6
Name LAST_QUARTER_DATE: [9]MASK!$EV$18
Name LT_Inflation: [9]MASK!$B$26
Name Modo_Operacao: [9]MASK!$C$671
Name Net_revenues: #REF!
Name NPV_FiscalBenfit: [9]MASK!$B$20
Name NPV_NOMINAL: [9]MASK!$B$38
Name Perp_Year: [9]MASK!$B$24
Name ProRata_Fiscal_Year: [9]MASK!$EV$12
Name RANGE_SCENARIOS: [9]MASK!$GD$16:$GN$16
Name REC: #REF!
Name ROW_SELECTION: [9]MASK!$FZ$16
Name SCENARIOS_CHOICE: [9]MASK!$AW$65
Name SharesOut_Diluted: [9]MASK!$B$9
Name Target_Ke_High: [9]MASK!$Q$6
Name Target_Ke_Low: [9]MASK!$Q$5
Name Valuation_Metric: [9]MASK!$C$672

Sheet DCF
C3: #VALUE! | F3: Premissas | I3: DCF Target
I4: Ke | J4: R$/Ação | K4: Upside
C5: # Ações (mil) | D5: =153000 -> 153000 | F5: Ke | G5: 0.14 | I5: =I6-1% -> 0.13 | J5: =SUM(E28:O28)/D5*1000 -> 22.037683 | K5: =J5/D6-1 -> 0.4682001
C6: Preço/Ação | D6: {=_FV(C3,"Preço")} -> 15.01 | F6: g | G6: 0.05 | I6: =G5 -> 0.14 | J6: =(SUM(E25:O25)/D5)*1000 -> 19.141142 | K6: =J6/D6-1 -> 0.27522596
C7: Market Cap (mil) | D7: =D5*D6 -> 2296530 | I7: =I6+1% -> 0.15 | J7: =SUM(E27:O27)/D5*1000 -> 16.856774 | K7: =J7/D6-1 -> 0.12303626
C10: DCF (R$ Mn) | E10: 2026 | F10: =E10+1 -> 2027 | G10: =F10+1 -> 2028 | H10: =G10+1 -> 2029 | I10: =H10+1 -> 2030 | J10: =I10+1 -> 2031 | K10: =J10+1 -> 2032 | L10: =K10+1 -> 2033 | M10: =L10+1 -> 2034 | N10: =M10+1 -> 2035 | O10: Perp
C12: Data | E12: 46387 | F12: =EOMONTH(E12,12) -> 46752 | G12: =EOMONTH(F12,12) -> 47118 | H12: =EOMONTH(G12,12) -> 47483 | I12: =EOMONTH(H12,12) -> 47848 | J12: =EOMONTH(I12,12) -> 48213 | K12: =EOMONTH(J12,12) -> 48579 | L12: =EOMONTH(K12,12) -> 48944 | M12: =EOMONTH(L12,12) -> 49309 | ... O12: =EOMONTH(N12,12) -> 50040
C13: Período | E13: =+(E12-TODAY())/365 -> 0.49315068 | F13: =+(F12-TODAY())/365 -> 1.4931507 | G13: =+(G12-TODAY())/365 -> 2.4958904 | H13: =+(H12-TODAY())/365 -> 3.4958904 | I13: =+(I12-TODAY())/365 -> 4.4958904 | J13: =+(J12-TODAY())/365 -> 5.4958904 | K13: =+(K12-TODAY())/365 -> 6.4986301 | L13: =+(L12-TODAY())/365 -> 7.4986301 | ... O13: =+(O12-TODAY())/365 -> 10.50137
C15: EBITDA | E15: =Modelo!AK91 -> 297.94183 | F15: =Modelo!AL91 -> 353.14299 | G15: =Modelo!AM91 -> 416.63398 | H15: =Modelo!AN91 -> 487.75857 | I15: =Modelo!AO91 -> 567.20042 | J15: =Modelo!AP91 -> 655.69482 | K15: =Modelo!AQ91 -> 754.03214 | L15: =Modelo!AR91 -> 863.06161 | ... N15: =Modelo!AT91 -> 1116.912 | O15: =N15*(1+$G$6) -> 1172.7576
C16: (-) Resultado financeiro | E16: =Modelo!AK92 -> -39.761249 | F16: =Modelo!AL92 -> -46.131487 | G16: =Modelo!AM92 -> -52.682328 | H16: =Modelo!AN92 -> -57.280853 | I16: =Modelo!AO92 -> -61.873279 | J16: =Modelo!AP92 -> -66.429598 | K16: =Modelo!AQ92 -> -70.915934 | L16: =Modelo!AR92 -> -75.294189 | ... N16: =Modelo!AT92 -> -83.550594 | O16: =N16*(1+$G$6) -> -87.728124
C17: (-) IR/CS | E17: =Modelo!AK93 -> -35.576112 | F17: =Modelo!AL93 -> -51.966339 | G17: =Modelo!AM93 -> -36.359147 | H17: =Modelo!AN93 -> -44.856219 | I17: =Modelo!AO93 -> -54.910463 | J17: =Modelo!AP93 -> -66.86585 | K17: =Modelo!AQ93 -> -80.898469 | L17: =Modelo!AR93 -> -97.203272 | ... N17: =Modelo!AT93 -> -137.50643 | O17: =N17*(1+$G$6) -> -144.38175
C18: (-) ∆ WKC | E18: =Modelo!AK94 -> -48.5517 | F18: =Modelo!AL94 -> -73.381562 | G18: =Modelo!AM94 -> -81.537316 | H18: =Modelo!AN94 -> -87.817429 | I18: =Modelo!AO94 -> -94.499064 | J18: =Modelo!AP94 -> -101.60558 | K18: =Modelo!AQ94 -> -109.16162 | L18: =Modelo!AR94 -> -117.1932 | ... N18: =Modelo!AT94 -> -134.79413 | O18: =N18*(1+$G$6) -> -141.53384
C19: (-) Adição Imobilizado | E19: =Modelo!AK95 -> -41.929642 | F19: =Modelo!AL95 -> -47.188925 | G19: =Modelo!AM95 -> -53.010723 | H19: =Modelo!AN95 -> -59.27071 | I19: =Modelo!AO95 -> -65.996638 | J19: =Modelo!AP95 -> -73.217866 | K19: =Modelo!AQ95 -> -80.965449 | L19: =Modelo!AR95 -> -89.272229 | ... N19: =Modelo!AT95 -> -107.70428 | O19: =N19*(1+$G$6) -> -113.08949
C20: (-) Adição Intangível | E20: =Modelo!AK96 -> -13.000867 | F20: =Modelo!AL96 -> -14.834889 | G20: =Modelo!AM96 -> -16.872748 | H20: =Modelo!AN96 -> -19.067565 | I20: =Modelo!AO96 -> -21.429376 | J20: =Modelo!AP96 -> -23.9688 | K20: =Modelo!AQ96 -> -26.697072 | L20: =Modelo!AR96 -> -29.626076 | ... N20: =Modelo!AT96 -> -36.137287 | O20: =N20*(1+$G$6) -> -37.944152
C21: (-) Depreciação Direito de Uso | E21: =Modelo!AK97 -> -22.246674 | F21: =Modelo!AL97 -> -25.861758 | G21: =Modelo!AM97 -> -29.782735 | H21: =Modelo!AN97 -> -34.031154 | I21: =Modelo!AO97 -> -38.629959 | J21: =Modelo!AP97 -> -43.603566 | K21: =Modelo!AQ97 -> -48.977959 | L21: =Modelo!AR97 -> -54.780782 | ... N21: =Modelo!AT97 -> -67.791218 | O21: =N21*(1+$G$6) -> -71.180779
C22: (+/-) Δ Dívida | E22: =Modelo!AK128-Modelo!AF128 -> 35.636814 | F22: =Modelo!AL128-Modelo!AK128 -> 18.873 | G22: =Modelo!AM128-Modelo!AL128 -> 0 | H22: =Modelo!AN128-Modelo!AM128 -> 0 | I22: =Modelo!AO128-Modelo!AN128 -> 0 | J22: =Modelo!AP128-Modelo!AO128 -> 0 | K22: =Modelo!AQ128-Modelo!AP128 -> 0 | L22: =Modelo!AR128-Modelo!AQ128 -> 0 | M22: =Modelo!AS128-Modelo!AR128 -> 0 | N22: =Modelo!AT128-Modelo!AS128 -> 0 | O22: =N22*(1+$G$6) -> 0
C23: FCFE | E23: =SUM(E15:E22) -> 132.5124 | F23: =SUM(F15:F22) -> 112.65103 | G23: =SUM(G15:G22) -> 146.38899 | H23: =SUM(H15:H22) -> 185.43464 | I23: =SUM(I15:I22) -> 229.86164 | J23: =SUM(J15:J22) -> 280.00356 | K23: =SUM(K15:K22) -> 336.41563 | L23: =SUM(L15:L22) -> 399.69186 | ... O23: =SUM(O15:O22) -> 576.89944
C25: FCFE Valor Presente | E25: =E23/(1+$G$5)^E13 -> 124.22067 | F25: =F23/(1+$G$5)^F13 -> 92.633406 | G25: =G23/(1+$G$5)^G13 -> 105.55532 | H25: =H23/(1+$G$5)^H13 -> 117.28912 | I25: =I23/(1+$G$5)^I13 -> 127.53475 | J25: =J23/(1+$G$5)^J13 -> 136.27642 | K25: =K23/(1+$G$5)^K13 -> 143.57294 | L25: =L23/(1+$G$5)^L13 -> 149.62938 | ... N25: =N23/(1+$G$5)^N13 -> 158.26784 | O25: =(O23/(G5-G6))/((1+G5)^O13) -> 1619.1188
C27: FCFE Valor Presente (Ke+1%) | E27: =E23/(1+$I$7)^E13 -> 123.6868 | F27: =F23/(1+$I$7)^F13 -> 91.433244 | G27: =G23/(1+$I$7)^G13 -> 103.27929 | H27: =H23/(1+$I$7)^H13 -> 113.76217 | I27: =I23/(1+$I$7)^I13 -> 122.62405 | J27: =J23/(1+$I$7)^J13 -> 129.88975 | K27: =K23/(1+$I$7)^K13 -> 135.65111 | L27: =L23/(1+$I$7)^L13 -> 140.14405 | ... N27: =N23/(1+$I$7)^N13 -> 145.66811 | O27: =(O23/(I7-G6))/((1+I7)^O13) -> 1329.504
C28: FCFE Valor Presente (Ke-1%) | E28: =E23/(1+$I$5)^E13 -> 124.76158 | F28: =F23/(1+$I$5)^F13 -> 93.860106 | G28: =G23/(1+$I$5)^G13 -> 107.90223 | H28: =H23/(1+$I$5)^H13 -> 120.95796 | I28: =I23/(1+$I$5)^I13 -> 132.688 | J28: =J23/(1+$I$5)^J13 -> 143.03761 | K28: =K23/(1+$I$5)^K13 -> 152.0334 | L28: =L23/(1+$I$5)^L13 -> 159.84891 | ... N28: =N23/(1+$I$5)^N13 -> 172.08314 | O28: =(O23/(I5-G6))/((1+I5)^O13) -> 1998.0841

Sheet Modelo
B2: TFCO | R$ MM | C2: 1T20 | D2: 2T20 | E2: 3T20 | F2: 4T20 | G2: 2020 | H2: 1T21 | I2: 2T21 | J2: 3T21 | K2: 4T21 | L2: 2021 | M2: 1T22 | N2: 2T22 | O2: 3T22 | P2: 4T22 | Q2: 2022 | R2: 1T23 | S2: 2T23 | T2: 3T23 | U2: 4T23 | V2: 2023 | W2: 1T24 | X2: 2T24 | Y2: 3T24 | Z2: 4T24 | AA2: 2024 | AB2: 1T25 | AC2: 2T25 | AD2: 3T25 | AE2: 4T25 | AF2: 2025 | AG2: 1T26 | AH2: 2T26 | AI2: 3T26 | AJ2: 4T26 | AK2: 2026 | AL2: 2027 | AM2: 2028 | AN2: 2029 | AO2: 2030 | AP2: 2031 | AQ2: 2032 | AR2: 2033 | AS2: 2034 | AT2: 2035 | AU2: x
AU3: x
A4: * | B4: 1 - Macro | AU4: x
AU5: x
B6: Selic Média | C6: 0.04177934 | D6: 0.03070842 | E6: 0.019402529 | F6: 0.019913713 | G6: =AVERAGE(C6:F6) -> 0.027951 | H6: 0.02 | I6: 0.035 | J6: 0.05 | K6: 0.0775 | L6: =AVERAGE(H6:K6) -> 0.045625 | M6: 0.105 | N6: 0.125 | O6: 0.136 | P6: 0.1375 | Q6: =AVERAGE(M6:P6) -> 0.125875 | R6: 0.1375 | S6: 0.1375 | T6: 0.1325 | U6: 0.1175 | V6: =AVERAGE(R6:U6) -> 0.13125 | W6: 0.111 | X6: 0.106 | Y6: 0.1058 | Z6: 0.114 | AA6: =AVERAGE(W6:Z6) -> 0.1092 | AB6: 0.136 | AC6: 0.147 | AD6: 0.15 | AE6: 0.15 | AF6: =AVERAGE(AB6:AE6) -> 0.14575 | AG6: 0.1483 | AH6: 0.138 | AI6: 0.13 | AJ6: 0.123 | AK6: =AVERAGE(AG6:AJ6) -> 0.134825 | AL6: 0.114 | AM6: 0.1 | AN6: 0.1 | AO6: 0.1 | AP6: 0.1 | AQ6: 0.1 | AR6: 0.1 | AS6: 0.1 | AT6: 0.1 | AU6: x
AU7: x
A8: * | B8: 2 - DRE | AU8: x
AU9: x
B10: Receita bruta | C10: =C167 -> 79.399 | D10: =D167 -> 32.289 | E10: =E167 -> 91.496 | F10: =F167 -> 165.739 | G10: =SUM(C10:F10) -> 368.923 | H10: =H167 -> 90.209 | I10: =I167 -> 129.463 | J10: =J167 -> 169.233 | K10: =K167 -> 208.349 | L10: =SUM(H10:K10) -> 597.254 | M10: =M167 -> 154.327 | N10: =N167 -> 177.559 | O10: =O167 -> 186.314 | P10: =P167 -> 257.899 | Q10: =SUM(M10:P10) -> 776.099 | R10: =R167 -> 195.898 | S10: =S167 -> 208.92 | T10: =T167 -> 221.746 | U10: =U167 -> 303.121 | V10: =SUM(R10:U10) -> 929.685 | W10: =W167 -> 223.426 | X10: =X167 -> 258.196 | Y10: =Y167 -> 269.476 | Z10: =Z167 -> 368.172 | AA10: =SUM(W10:Z10) -> 1119.27 | AB10: =AB167 -> 288.208 | AC10: =AC167 -> 324.73 | AD10: =AD167 -> 360.077 | AE10: =AE167 -> 437.099 | AF10: =SUM(AB10:AE10) -> 1410.114 | AG10: =AG167 -> 344.944 | AH10: =AH167 -> 357.84012 | AI10: =AI167 -> 377.82457 | AJ10: =AJ167 -> 504.64758 | AK10: =SUM(AG10:AJ10) -> 1585.2563 | AL10: =AL167 -> 1808.8871 | AM10: =AM167 -> 2057.3727 | AN10: =AN167 -> 2324.997 | AO10: =AO167 -> 2612.9836 | AP10: =AP167 -> 2922.6273 | AQ10: =AQ167 -> 3255.2982 | AR10: =AR167 -> 3612.4454 | AS10: =AS167 -> 3995.6015 | AT10: =AT167 -> 4406.3877 | AU10: x
B11: % yoy | H11: =H10/C10-1 -> 0.13614781 | I11: =I10/D10-1 -> 3.0095079 | J11: =J10/E10-1 -> 0.84962184 | K11: =K10/F10-1 -> 0.25709097 | L11: =L10/SUM(C10:F10)-1 -> 0.61891235 | M11: =M10/H10-1 -> 0.71077165 | N11: =N10/I10-1 -> 0.37150383 | O11: =O10/J10-1 -> 0.10093185 | P11: =P10/K10-1 -> 0.23782212 | Q11: =Q10/SUM(H10:K10)-1 -> 0.29944546 | R11: =R10/M10-1 -> 0.26936959 | S11: =S10/N10-1 -> 0.17662298 | T11: =T10/O10-1 -> 0.19017358 | U11: =U10/P10-1 -> 0.17534771 | V11: =V10/SUM(M10:P10)-1 -> 0.19789486 | W11: =W10/R10-1 -> 0.14052211 | X11: =X10/S10-1 -> 0.23586062 | Y11: =Y10/T10-1 -> 0.21524627 | Z11: =Z10/U10-1 -> 0.21460407 | AA11: =AA10/SUM(R10:U10)-1 -> 0.20392391 | AB11: =AB10/W10-1 -> 0.28994835 | AC11: =AC10/X10-1 -> 0.25768796 | AD11: =AD10/Y10-1 -> 0.33621176 | AE11: =AE10/Z10-1 -> 0.18721413 | AF11: =AF10/SUM(W10:Z10)-1 -> 0.25985151 | AG11: =AG10/AB10-1 -> 0.19685782 | AH11: =AH10/AC10-1 -> 0.101962 | AI11: =AI10/AD10-1 -> 0.049288251 | AJ11: =AJ10/AE10-1 -> 0.15453839 | AK11: =AK10/SUM(AB10:AE10)-1 -> 0.12420433 | AL11: =AL10/AK10-1 -> 0.14106922 | AM11: =AM10/AL10-1 -> 0.13736931 | AN11: =AN10/AM10-1 -> 0.1300806 | AO11: =AO10/AN10-1 -> 0.12386537 | AP11: =AP10/AO10-1 -> 0.118502 | AQ11: =AQ10/AP10-1 -> 0.11382596 | AR11: =AR10/AQ10-1 -> 0.10971257 | AS11: =AS10/AR10-1 -> 0.1060656 | AT11: =AT10/AS10-1 -> 0.10280958 | AU11: x
AU12: x
B13: (-) Deduções | C13: =C16-C10 -> -23.265 | D13: =D16-D10 -> -8.856 | E13: =E16-E10 -> -25.228 | F13: =F16-F10 -> -44.25447 | G13: =SUM(C13:F13) -> -101.60347 | H13: =H16-H10 -> -26.496 | I13: =I16-I10 -> -35.024 | J13: =J16-J10 -> -44.451986 | K13: =K16-K10 -> -56.690169 | L13: =SUM(H13:K13) -> -162.66216 | M13: =M16-M10 -> -41.803 | N13: =N16-N10 -> -46.116 | O13: =O16-O10 -> -48.167 | P13: =P16-P10 -> -72.587 | Q13: =SUM(M13:P13) -> -208.673 | R13: =R16-R10 -> -54.208 | S13: =S16-S10 -> -53.144612 | T13: =T16-T10 -> -57.468275 | U13: =U16-U10 -> -81.174 | V13: =SUM(R13:U13) -> -245.99489 | W13: =W16-W10 -> -61.295 | X13: =X16-X10 -> -66.194 | Y13: =Y16-Y10 -> -65.141 | Z13: =Z16-Z10 -> -94.881 | AA13: =SUM(W13:Z13) -> -287.511 | AB13: =AB16-AB10 -> -75.422 | AC13: =AC16-AC10 -> -82.639 | AD13: =AD16-AD10 -> -91.548 | AE13: =AE16-AE10 -> -113.993 | AF13: =SUM(AB13:AE13) -> -363.602 | AG13: =AG16-AG10 -> -93.786 | AH13: =AH16-AH10 -> -97.292295 | AI13: =AI16-AI10 -> -102.72582 | AJ13: =AJ16-AJ10 -> -137.20742 | AK13: =SUM(AG13:AJ13) -> -431.01154 | AL13: =AL16-AL10 -> -491.814 | AM13: =AM16-AM10 -> -559.37415 | AN13: =AN16-AN10 -> -632.13787 | AO13: =AO16-AO10 -> -710.43786 | AP13: =AP16-AP10 -> -794.62617 | AQ13: =AQ16-AQ10 -> -885.07525 | AR13: =AR16-AR10 -> -982.17914 | AS13: =AS16-AS10 -> -1086.3546 | AT13: =AT16-AT10 -> -1198.0422 | AU13: x
B14: % RB | C14: =C13/C10 -> -0.29301377 | D14: =D13/D10 -> -0.27427297 | E14: =E13/E10 -> -0.2757279 | F14: =F13/F10 -> -0.26701302 | G14: =G13/G10 -> -0.27540563 | H14: =H13/H10 -> -0.29371792 | I14: =I13/I10 -> -0.27053289 | J14: =J13/J10 -> -0.26266737 | ... AT14: =AT13/AT10 -> -0.27188761 | AU14: x
AU15: x
B16: Receita líquida | C16: 56.134 | D16: 23.433 | E16: 66.268 | F16: 121.48453 | G16: =SUM(C16:F16) -> 267.31953 | H16: 63.713 | I16: 94.439 | J16: 124.78101 | K16: 151.65883 | L16: =SUM(H16:K16) -> 434.59184 | M16: 112.524 | N16: 131.443 | O16: 138.147 | P16: 185.312 | Q16: =SUM(M16:P16) -> 567.426 | R16: 141.69 | S16: 155.77539 | T16: 164.27772 | U16: 221.947 | V16: =SUM(R16:U16) -> 683.69011 | W16: 162.131 | X16: 192.002 | Y16: 204.335 | Z16: 273.291 | AA16: =SUM(W16:Z16) -> 831.759 | AB16: 212.786 | AC16: 242.091 | AD16: 268.529 | AE16: 323.106 | AF16: =SUM(AB16:AE16) -> 1046.512 | AG16: 251.158 | AH16: =AH199 -> 260.54783 | AI16: =AI199 -> 275.09875 | AJ16: =AJ199 -> 367.44015 | AK16: =SUM(AG16:AJ16) -> 1154.2447 | AL16: =AL199 -> 1317.0731 | AM16: =AM199 -> 1497.9986 | AN16: =AN199 -> 1692.8591 | AO16: =AO199 -> 1902.5457 | AP16: =AP199 -> 2128.0012 | AQ16: =AQ199 -> 2370.223 | AR16: =AR199 -> 2630.2662 | AS16: =AS199 -> 2909.247 | AT16: =AT199 -> 3208.3455 | AU16: x
B17: % yoy | H17: =H16/C16-1 -> 0.13501621 | I17: =I16/D16-1 -> 3.0301711 | J17: =J16/E16-1 -> 0.8829754 | K17: =K16/F16-1 -> 0.24837978 | L17: =L16/SUM(C16:F16)-1 -> 0.62573922 | M17: =M16/H16-1 -> 0.76610739 | N17: =N16/I16-1 -> 0.39182965 | O17: =O16/J16-1 -> 0.10711555 | P17: =P16/K16-1 -> 0.22190049 | Q17: =Q16/SUM(H16:K16)-1 -> 0.30565267 | R17: =R16/M16-1 -> 0.25919804 | S17: =S16/N16-1 -> 0.18511741 | T17: =T16/O16-1 -> 0.18915159 | U17: =U16/P16-1 -> 0.19769362 | V17: =V16/SUM(M16:P16)-1 -> 0.2048974 | W17: =W16/R16-1 -> 0.14426565 | X17: =X16/S16-1 -> 0.23255671 | Y17: =Y16/T16-1 -> 0.24383875 | Z17: =Z16/U16-1 -> 0.23133451 | AA17: =AA16/SUM(R16:U16)-1 -> 0.2165731 | AB17: =AB16/W16-1 -> 0.31243254 | AC17: =AC16/X16-1 -> 0.26087749 | AD17: =AD16/Y16-1 -> 0.31416057 | AE17: =AE16/Z16-1 -> 0.18227823 | AF17: =AF16/SUM(W16:Z16)-1 -> 0.25819138 | AG17: =AG16/AB16-1 -> 0.18033141 | AH17: =AH16/AC16-1 -> 0.076239205 | AI17: =AI16/AD16-1 -> 0.024465689 | AJ17: =AJ16/AE16-1 -> 0.13721241 | AK17: =AK16/SUM(AB16:AE16)-1 -> 0.10294457 | AL17: =AL16/AK16-1 -> 0.14106922 | AM17: =AM16/AL16-1 -> 0.13736931 | AN17: =AN16/AM16-1 -> 0.1300806 | AO17: =AO16/AN16-1 -> 0.12386537 | AP17: =AP16/AO16-1 -> 0.118502 | AQ17: =AQ16/AP16-1 -> 0.11382596 | AR17: =AR16/AQ16-1 -> 0.10971257 | AS17: =AS16/AR16-1 -> 0.1060656 | AT17: =AT16/AS16-1 -> 0.10280958 | AU17: x
AU18: x
B19: (-) Custos | C19: =C519 -> -26.721 | D19: =D519 -> -9.689 | E19: =E519 -> -27.264 | F19: =F519 -> -47.755108 | G19: =SUM(C19:F19) -> -111.42911 | H19: =H519 -> -22.91 | I19: =I519 -> -38.13169 | J19: =J519 -> -54.499536 | K19: =K519 -> -59.000391 | L19: =SUM(H19:K19) -> -174.54162 | M19: =M519 -> -44.85709 | N19: =N519 -> -60.145 | O19: =O519 -> -58.781319 | P19: =P519 -> -76.366 | Q19: =SUM(M19:P19) -> -240.14941 | R19: =R519 -> -57.854952 | S19: =S519 -> -66.332 | T19: =T519 -> -69.142 | U19: =U519 -> -93.332376 | V19: =SUM(R19:U19) -> -286.66133 | W19: =W519 -> -65.910136 | X19: =X519 -> -84.517 | Y19: =Y519 -> -90.405 | Z19: =Z519 -> -118.127 | AA19: =SUM(W19:Z19) -> -358.95914 | AB19: =AB519 -> -82.463219 | AC19: =AC519 -> -102.751 | AD19: =AD519 -> -126.1176 | AE19: =AE519 -> -131.973 | AF19: =SUM(AB19:AE19) -> -443.30482 | AG19: =AG519 -> -100.4 | AH19: =AH21-AH16 -> -103.5022 | AI19: =AI21-AI16 -> -108.59478 | AJ19: =AJ21-AJ16 -> -144.1278 | AK19: =SUM(AG19:AJ19) -> -456.62478 | AL19: =AL21-AL16 -> -507.86975 | AM19: =AM21-AM16 -> -562.65548 | AN19: =AN21-AN16 -> -618.91745 | AO19: =AO21-AO16 -> -676.55443 | AP19: =AP21-AP16 -> -735.44747 | AQ19: =AQ21-AQ16 -> -795.45825 | AR19: =AR21-AR16 -> -856.42736 | AS19: =AS21-AS16 -> -918.17237 | AT19: =AT21-AT16 -> -980.48584 | AU19: x
AU20: x
B21: Lucro bruto | C21: =C16+C19 -> 29.413 | D21: =D16+D19 -> 13.744 | E21: =E16+E19 -> 39.004 | F21: =F16+F19 -> 73.729421 | G21: =SUM(C21:F21) -> 155.89042 | H21: =H16+H19 -> 40.803 | I21: =I16+I19 -> 56.30731 | J21: =J16+J19 -> 70.281478 | K21: =K16+K19 -> 92.65844 | L21: =SUM(H21:K21) -> 260.05023 | M21: =M16+M19 -> 67.66691 | N21: =N16+N19 -> 71.298 | O21: =O16+O19 -> 79.365681 | P21: =P16+P19 -> 108.946 | Q21: =SUM(M21:P21) -> 327.27659 | R21: =R16+R19 -> 83.835048 | S21: =S16+S19 -> 89.443388 | T21: =T16+T19 -> 95.135725 | U21: =U16+U19 -> 128.61462 | V21: =SUM(R21:U21) -> 397.02878 | W21: =W16+W19 -> 96.220864 | X21: =X16+X19 -> 107.485 | Y21: =Y16+Y19 -> 113.93 | Z21: =Z16+Z19 -> 155.164 | AA21: =SUM(W21:Z21) -> 472.79986 | AB21: =AB16+AB19 -> 130.32278 | AC21: =AC16+AC19 -> 139.34 | AD21: =AD16+AD19 -> 142.4114 | AE21: =AE16+AE19 -> 191.133 | AF21: =SUM(AB21:AE21) -> 603.20718 | AG21: =AG16+AG19 -> 150.758 | AH21: =AH22*AH16 -> 157.04563 | AI21: =AI22*AI16 -> 166.50397 | AJ21: =AJ22*AJ16 -> 223.31235 | AK21: =SUM(AG21:AJ21) -> 697.61995 | AL21: =AL22*AL16 -> 809.20338 | AM21: =AM22*AM16 -> 935.34307 | AN21: =AN22*AN16 -> 1073.9417 | AO21: =AO22*AO16 -> 1225.9913 | AP21: =AP22*AP16 -> 1392.5537 | AQ21: =AQ22*AQ16 -> 1574.7647 | AR21: =AR22*AR16 -> 1773.8389 | AS21: =AS22*AS16 -> 1991.0746 | AT21: =AT22*AT16 -> 2227.8596 | AU21: x
B22: % margem bruta | C22: =C21/C16 -> 0.52397834 | D22: =D21/D16 -> 0.58652328 | E22: =E21/E16 -> 0.58857971 | F22: =F21/F16 -> 0.60690379 | G22: =G21/G16 -> 0.58316136 | H22: =H21/H16 -> 0.64041875 | I22: =I21/I16 -> 0.59622942 | J22: =J21/J16 -> 0.56323855 | ... AG22: =AG21/AG16 -> 0.60025163 | AH22: =AG22+0.25% -> 0.60275163 | AI22: =AH22+0.25% -> 0.60525163 | AJ22: =AI22+0.25% -> 0.60775163 | AK22: =AK21/AK16 -> 0.60439518 | AL22: =AK22+0.01 -> 0.61439518 | AM22: =AL22+0.01 -> 0.62439518 | AN22: =AM22+0.01 -> 0.63439518 | AO22: =AN22+0.01 -> 0.64439518 | AP22: =AO22+0.01 -> 0.65439518 | AQ22: =AP22+0.01 -> 0.66439518 | AR22: =AQ22+0.01 -> 0.67439518 | AS22: =AR22+0.01 -> 0.68439518 | AT22: =AS22+0.01 -> 0.69439518 | AU22: x
AU23: x
B24: (-) Despesas | C24: =C520 -> -24.898 | D24: =D520 -> -14.406 | E24: =E520 -> -25.67 | F24: =F520 -> -39.466934 | G24: =SUM(C24:F24) -> -104.44093 | H24: =H520 -> -29.113 | I24: =I520 -> -36.716265 | J24: =J520 -> -44.101064 | K24: =K520 -> -48.663341 | L24: =SUM(H24:K24) -> -158.59367 | M24: =M520 -> -38.097992 | N24: =N520 -> -42.380252 | O24: =O520 -> -45.374634 | P24: =P520 -> -61.495478 | Q24: =SUM(M24:P24) -> -187.34836 | R24: =R520 -> -46.006 | S24: =S520 -> -49.672 | T24: =T520 -> -53.848 | U24: =U520 -> -75.877 | V24: =SUM(R24:U24) -> -225.403 | W24: =W520 -> -55.115 | X24: =X520 -> -63.305 | Y24: =Y520 -> -69.697375 | Z24: =Z520 -> -92.196 | AA24: =SUM(W24:Z24) -> -280.31338 | AB24: =AB520 -> -72.225979 | AC24: =AC520 -> -80.662 | AD24: =AD520 -> -87.259747 | AE24: =AE520 -> -107.428 | AF24: =SUM(AB24:AE24) -> -347.57573 | AG24: =AG520 -> -86.444 | AH24: =AH25*AH16 -> -89.675807 | AI24: =AI25*AI16 -> -94.683968 | AJ24: =AJ25*AJ16 -> -126.46619 | AK24: =SUM(AG24:AJ24) -> -397.26997 | AL24: =AL25*AL16 -> -453.31253 | AM24: =AM25*AM16 -> -515.58376 | AN24: =AN25*AN16 -> -582.65121 | AO24: =AO25*AO16 -> -654.82151 | AP24: =AP25*AP16 -> -732.41917 | AQ24: =AQ25*AQ16 -> -815.78749 | AR24: =AR25*AR16 -> -905.28963 | AS24: =AS25*AS16 -> -1001.3097 | AT24: =AT25*AT16 -> -1104.254 | AU24: x
B25: % RL | C25: =C24/C$16 -> -0.4435458 | D25: =D24/D$16 -> -0.61477404 | E25: =E24/E$16 -> -0.38736645 | F25: =F24/F$16 -> -0.3248721 | G25: =G24/G16 -> -0.39069698 | H25: =H24/H$16 -> -0.45693971 | I25: =I24/I$16 -> -0.38878286 | J25: =J24/J$16 -> -0.35342768 | K25: =K24/K$16 -> -0.32087377 | L25: =L24/L16 -> -0.36492555 | M25: =M24/M$16 -> -0.33857659 | N25: =N24/N$16 -> -0.32242304 | O25: =O24/O$16 -> -0.32845182 | P25: =P24/P$16 -> -0.33184833 | Q25: =Q24/Q16 -> -0.33017231 | R25: =R24/R$16 -> -0.32469476 | S25: =S24/S$16 -> -0.31886937 | T25: =T24/T$16 -> -0.32778638 | U25: =U24/U$16 -> -0.34186991 | V25: =V24/V16 -> -0.32968591 | W25: =W24/W$16 -> -0.33994116 | X25: =X24/X$16 -> -0.32971011 | Y25: =Y24/Y$16 -> -0.34109367 | Z25: =Z24/Z$16 -> -0.33735469 | AA25: =AA24/AA16 -> -0.33701273 | AB25: =AB24/AB$16 -> -0.33943013 | AC25: =AC24/AC$16 -> -0.33318876 | AD25: =AD24/AD$16 -> -0.32495465 | AE25: =AE24/AE$16 -> -0.33248531 | AF25: =AF24/AF16 -> -0.3321278 | AG25: =AG24/AG$16 -> -0.34418175 | AH25: =AG25 -> -0.34418175 | AI25: =AH25 -> -0.34418175 | AJ25: =AI25 -> -0.34418175 | AK25: =AK24/AK16 -> -0.34418175 | AL25: =AK25 -> -0.34418175 | AM25: =AL25 -> -0.34418175 | AN25: =AM25 -> -0.34418175 | AO25: =AN25 -> -0.34418175 | AP25: =AO25 -> -0.34418175 | AQ25: =AP25 -> -0.34418175 | AR25: =AQ25 -> -0.34418175 | AS25: =AR25 -> -0.34418175 | AT25: =AS25 -> -0.34418175 | AU25: x
AU26: x
B27: (-) Outras receitas (despesas) | C27: -0.308 | D27: 1.727 | E27: -0.416 | F27: -0.91179633 | G27: =SUM(C27:F27) -> 0.09120367 | H27: -0.7 | I27: 0.565 | J27: 0.85291429 | K27: -0.29653536 | L27: =SUM(H27:K27) -> 0.42137893 | M27: 2.802877 | N27: -0.123 | O27: 0.248 | P27: 0.905 | Q27: =SUM(M27:P27) -> 3.832877 | R27: -0.05036613 | S27: 1.0992736 | T27: -0.00735135 | U27: 1.063 | V27: =SUM(R27:U27) -> 2.1045561 | W27: 0.30744589 | X27: -0.339 | Y27: 0.77443631 | Z27: 2.996074 | AA27: =SUM(W27:Z27) -> 3.7389562 | AB27: 0.48981088 | AC27: -0.38 | AD27: 1.721 | AE27: -8.049 | AF27: =SUM(AB27:AE27) -> -6.2181891 | AG27: -0.524 | AH27: =AH28*AH16 -> -0.54359033 | AI27: =AI28*AI16 -> -0.57394844 | AJ27: =AJ28*AJ16 -> -0.76660365 | AK27: =SUM(AG27:AJ27) -> -2.4081424 | AL27: =AL28*AL16 -> -2.7478572 | AM27: =AM28*AM16 -> -3.1253284 | AN27: =AN28*AN16 -> -3.531873 | AO27: =AO28*AO16 -> -3.9693498 | AP27: =AP28*AP16 -> -4.4397257 | AQ27: =AQ28*AQ16 -> -4.9450817 | AR27: =AR28*AR16 -> -5.4876193 | AS27: =AS28*AS16 -> -6.069667 | AT27: =AT28*AT16 -> -6.6936869 | AU27: x
B28: % RL | C28: =C27/C$16 -> -0.0054868707 | D28: =D27/D$16 -> 0.073699484 | E28: =E27/E$16 -> -0.0062775397 | F28: =F27/F$16 -> -0.0075054522 | G28: =G27/G16 -> 0.00034117848 | H28: =H27/H$16 -> -0.010986769 | I28: =I27/I$16 -> 0.0059826978 | J28: =J27/J$16 -> 0.006835289 | K28: =K27/K$16 -> -0.0019552792 | L28: =L27/L16 -> 0.00096959696 | M28: =M27/M$16 -> 0.024909148 | N28: =N27/N$16 -> -0.00093576683 | O28: =O27/O$16 -> 0.0017951892 | P28: =P27/P$16 -> 0.0048836557 | Q28: =Q27/Q16 -> 0.006754849 | R28: =R27/R$16 -> -0.00035546708 | S28: =S27/S$16 -> 0.007056786 | T28: =T27/T$16 -> -4.4749524e-05 | U28: =U27/U$16 -> 0.0047894317 | V28: =V27/V16 -> 0.003078231 | W28: =W27/W$16 -> 0.0018962807 | X28: =X27/X$16 -> -0.0017656066 | Y28: =Y27/Y$16 -> 0.0037900326 | Z28: =Z27/Z$16 -> 0.010962944 | AA28: =AA27/AA16 -> 0.0044952399 | AB28: =AB27/AB$16 -> 0.0023018943 | AC28: =AC27/AC$16 -> -0.0015696577 | AD28: =AD27/AD$16 -> 0.0064089912 | AE28: =AE27/AE$16 -> -0.024911329 | AF28: =AF27/AF16 -> -0.005941823 | AG28: =AG27/AG$16 -> -0.0020863361 | AH28: =AG28 -> -0.0020863361 | AI28: =AH28 -> -0.0020863361 | AJ28: =AI28 -> -0.0020863361 | AK28: =AK27/AK16 -> -0.0020863361 | AL28: =AK28 -> -0.0020863361 | AM28: =AL28 -> -0.0020863361 | AN28: =AM28 -> -0.0020863361 | AO28: =AN28 -> -0.0020863361 | AP28: =AO28 -> -0.0020863361 | AQ28: =AP28 -> -0.0020863361 | AR28: =AQ28 -> -0.0020863361 | AS28: =AR28 -> -0.0020863361 | AT28: =AS28 -> -0.0020863361 | AU28: x
AU29: x
B30: EBITDA | C30: =C21+C24+C27 -> 4.207 | D30: =D21+D24+D27 -> 1.065 | E30: =E21+E24+E27 -> 12.918 | F30: =F21+F24+F27 -> 33.350691 | G30: =SUM(C30:F30) -> 51.540691 | H30: =H21+H24+H27 -> 10.99 | I30: =I21+I24+I27 -> 20.156045 | J30: =J21+J24+J27 -> 27.033328 | K30: =K21+K24+K27 -> 43.698564 | L30: =SUM(H30:K30) -> 101.87794 | M30: =M21+M24+M27 -> 32.371795 | N30: =N21+N24+N27 -> 28.794748 | O30: =O21+O24+O27 -> 34.239047 | P30: =P21+P24+P27 -> 48.355522 | Q30: =SUM(M30:P30) -> 143.76111 | R30: =R21+R24+R27 -> 37.778682 | S30: =S21+S24+S27 -> 40.870661 | T30: =T21+T24+T27 -> 41.280373 | U30: =U21+U24+U27 -> 53.800624 | V30: =SUM(R30:U30) -> 173.73034 | W30: =W21+W24+W27 -> 41.41331 | X30: =X21+X24+X27 -> 43.841 | Y30: =Y21+Y24+Y27 -> 45.007061 | Z30: =Z21+Z24+Z27 -> 65.964073 | AA30: =SUM(W30:Z30) -> 196.22544 | AB30: =AB21+AB24+AB27 -> 58.586613 | AC30: =AC21+AC24+AC27 -> 58.298 | AD30: =AD21+AD24+AD27 -> 56.872656 | AE30: =AE21+AE24+AE27 -> 75.656 | AF30: =SUM(AB30:AE30) -> 249.41327 | AG30: =AG21+AG24+AG27 -> 63.79 | AH30: =AH21+AH24+AH27 -> 66.826231 | AI30: =AI21+AI24+AI27 -> 71.24605 | AJ30: =AJ21+AJ24+AJ27 -> 96.079555 | AK30: =SUM(AG30:AJ30) -> 297.94183 | AL30: =AL21+AL24+AL27 -> 353.14299 | AM30: =AM21+AM24+AM27 -> 416.63398 | AN30: =AN21+AN24+AN27 -> 487.75857 | AO30: =AO21+AO24+AO27 -> 567.20042 | AP30: =AP21+AP24+AP27 -> 655.69482 | AQ30: =AQ21+AQ24+AQ27 -> 754.03214 | AR30: =AR21+AR24+AR27 -> 863.06161 | AS30: =AS21+AS24+AS27 -> 983.69522 | AT30: =AT21+AT24+AT27 -> 1116.912 | AU30: x
B31: % margem ebitda | C31: =C30/C$16 -> 0.074945666 | D31: =D30/D$16 -> 0.045448726 | E31: =E30/E$16 -> 0.19493572 | F31: =F30/F$16 -> 0.27452624 | G31: =G30/G16 -> 0.19280556 | H31: =H30/H$16 -> 0.17249227 | I31: =I30/I$16 -> 0.21342925 | J31: =J30/J$16 -> 0.21664617 | K31: =K30/K$16 -> 0.28813729 | L31: =L30/L16 -> 0.23442211 | M31: =M30/M$16 -> 0.28768792 | N31: =N30/N$16 -> 0.21906643 | O31: =O30/O$16 -> 0.24784503 | P31: =P30/P$16 -> 0.26094112 | Q31: =Q30/Q16 -> 0.25335658 | R31: =R30/R$16 -> 0.26662913 | S31: =S30/S$16 -> 0.26236918 | T31: =T30/T$16 -> 0.25128406 | U31: =U30/U$16 -> 0.24240302 | V31: =V30/V16 -> 0.25410685 | W31: =W30/W$16 -> 0.25543116 | X31: =X30/X$16 -> 0.22833616 | Y31: =Y30/Y$16 -> 0.22026114 | Z31: =Z30/Z$16 -> 0.24136936 | AA31: =AA30/AA16 -> 0.23591623 | AB31: =AB30/AB$16 -> 0.27533114 | AC31: =AC30/AC$16 -> 0.24081027 | AD31: =AD30/AD$16 -> 0.21179335 | AE31: =AE30/AE$16 -> 0.23415226 | AF31: =AF30/AF16 -> 0.23832815 | AG31: =AG30/AG$16 -> 0.25398355 | AH31: =AH30/AH$16 -> 0.25648355 | AI31: =AI30/AI$16 -> 0.25898355 | AJ31: =AJ30/AJ$16 -> 0.26148355 | AK31: =AK30/AK16 -> 0.25812709 | AL31: =AL30/AL16 -> 0.26812709 | AM31: =AM30/AM16 -> 0.27812709 | AN31: =AN30/AN16 -> 0.28812709 | AO31: =AO30/AO16 -> 0.29812709 | AP31: =AP30/AP16 -> 0.30812709 | AQ31: =AQ30/AQ16 -> 0.31812709 | AR31: =AR30/AR16 -> 0.32812709 | ... AT31: =AT30/AT16 -> 0.34812709 | AU31: x
AU32: x
B33: (-) D&A | C33: =C509 -> -2.834 | D33: =D509 -> -2.828 | E33: =E509 -> -2.794 | F33: =F509 -> -2.619 | G33: =SUM(C33:F33) -> -11.075 | H33: =H509 -> -2.442 | I33: =I509 -> -2.427 | J33: =J509 -> -3.326 | K33: =K509 -> -3.315 | L33: =SUM(H33:K33) -> -11.51 | M33: =M509 -> -4 | N33: =N509 -> -4.308 | O33: =O509 -> -4.691 | P33: =P509 -> -5.545 | Q33: =SUM(M33:P33) -> -18.544 | R33: =R509 -> -5.817 | S33: =S509 -> -6.192 | T33: =T509 -> -6.375 | U33: =U509 -> -6.633 | V33: =SUM(R33:U33) -> -25.017 | W33: =W509 -> -7.098 | X33: =X509 -> -7.936 | Y33: =Y509 -> -8.253 | Z33: =Z509 -> -8.732 | AA33: =SUM(W33:Z33) -> -32.019 | AB33: =AB509 -> -8.266 | AC33: =AC509 -> -9.201 | AD33: =AD509 -> -9.42 | AE33: =AE509 -> -10.072 | AF33: =SUM(AB33:AE33) -> -36.959 | AG33: =AG509 -> -9.95 | AH33: =AH513 -> -11.255132 | AI33: =AI513 -> -11.558526 | AJ33: =AJ513 -> -12.362183 | AK33: =SUM(AG33:AJ33) -> -45.125841 | AL33: =AL513 -> -55.451571 | AM33: =AM513 -> -65.692383 | AN33: =AN513 -> -76.563593 | AO33: =AO513 -> -88.147027 | AP33: =AP513 -> -100.52105 | AQ33: =AQ513 -> -113.76236 | AR33: =AR513 -> -127.94735 | AS33: =AS513 -> -143.15321 | AT33: =AT513 -> -159.45883 | AU33: x
AU34: x
B35: EBIT | C35: =C30+C33 -> 1.373 | D35: =D30+D33 -> -1.763 | E35: =E30+E33 -> 10.124 | F35: =F30+F33 -> 30.731691 | G35: =SUM(C35:F35) -> 40.465691 | H35: =H30+H33 -> 8.548 | I35: =I30+I33 -> 17.729045 | J35: =J30+J33 -> 23.707328 | K35: =K30+K33 -> 40.383564 | L35: =SUM(H35:K35) -> 90.367937 | M35: =M30+M33 -> 28.371795 | N35: =N30+N33 -> 24.486748 | O35: =O30+O33 -> 29.548047 | P35: =P30+P33 -> 42.810522 | Q35: =SUM(M35:P35) -> 125.21711 | R35: =R30+R33 -> 31.961682 | S35: =S30+S33 -> 34.678661 | T35: =T30+T33 -> 34.905373 | U35: =U30+U33 -> 47.167624 | V35: =SUM(R35:U35) -> 148.71334 | W35: =W30+W33 -> 34.31531 | X35: =X30+X33 -> 35.905 | Y35: =Y30+Y33 -> 36.754061 | Z35: =Z30+Z33 -> 57.232073 | AA35: =SUM(W35:Z35) -> 164.20644 | AB35: =AB30+AB33 -> 50.320613 | AC35: =AC30+AC33 -> 49.097 | AD35: =AD30+AD33 -> 47.452656 | AE35: =AE30+AE33 -> 65.584 | AF35: =SUM(AB35:AE35) -> 212.45427 | AG35: =AG30+AG33 -> 53.84 | AH35: =AH30+AH33 -> 55.571099 | AI35: =AI30+AI33 -> 59.687524 | AJ35: =AJ30+AJ33 -> 83.717371 | AK35: =SUM(AG35:AJ35) -> 252.81599 | AL35: =AL30+AL33 -> 297.69142 | AM35: =AM30+AM33 -> 350.9416 | AN35: =AN30+AN33 -> 411.19498 | AO35: =AO30+AO33 -> 479.0534 | AP35: =AP30+AP33 -> 555.17376 | AQ35: =AQ30+AQ33 -> 640.26978 | AR35: =AR30+AR33 -> 735.11426 | AS35: =AS30+AS33 -> 840.54201 | AT35: =AT30+AT33 -> 957.45315 | AU35: x
B36: % margem ebit | C36: =C35/C$16 -> 0.024459329 | D36: =D35/D$16 -> -0.075235779 | E36: =E35/E$16 -> 0.15277359 | F36: =F35/F$16 -> 0.25296794 | G36: =G35/G16 -> 0.15137574 | H36: =H35/H$16 -> 0.13416414 | I36: =I35/I$16 -> 0.18773012 | J36: =J35/J$16 -> 0.18999147 | K36: =K35/K$16 -> 0.26627901 | L36: =L35/L16 -> 0.20793749 | M36: =M35/M$16 -> 0.25213995 | N36: =N35/N$16 -> 0.18629176 | O36: =O35/O$16 -> 0.21388845 | P36: =P35/P$16 -> 0.23101862 | Q36: =Q35/Q16 -> 0.22067567 | R36: =R35/R$16 -> 0.22557472 | S36: =S35/S$16 -> 0.22261964 | T36: =T35/T$16 -> 0.21247782 | U36: =U35/U$16 -> 0.21251751 | V36: =V35/V16 -> 0.21751571 | W36: =W35/W$16 -> 0.21165175 | X36: =X35/X$16 -> 0.18700326 | Y36: =Y35/Y$16 -> 0.17987159 | Z36: =Z35/Z$16 -> 0.20941807 | AA36: =AA35/AA16 -> 0.1974207 | AB36: =AB35/AB$16 -> 0.2364846 | AC36: =AC35/AC$16 -> 0.2028039 | AD36: =AD35/AD$16 -> 0.17671334 | AE36: =AE35/AE$16 -> 0.20297983 | AF36: =AF35/AF16 -> 0.20301178 | AG36: =AG35/AG$16 -> 0.21436705 | AH36: =AH35/AH$16 -> 0.2132856 | AI36: =AI35/AI$16 -> 0.21696763 | AJ36: =AJ35/AJ$16 -> 0.22783948 | AK36: =AK35/AK16 -> 0.21903154 | AL36: =AL35/AL16 -> 0.22602497 | AM36: =AM35/AM16 -> 0.23427366 | AN36: =AN35/AN16 -> 0.24289971 | AO36: =AO35/AO16 -> 0.251796 | AP36: =AP35/AP16 -> 0.26088978 | AQ36: =AQ35/AQ16 -> 0.27013061 | AR36: =AR35/AR16 -> 0.27948283 | ... AT36: =AT35/AT16 -> 0.29842583 | AU36: x
AU37: x
B38: (-) Resultado financeiro | C38: =C308 -> -1.127 | D38: =D308 -> -0.9 | E38: =E308 -> -0.717 | F38: =F308 -> -2.3635138 | G38: =SUM(C38:F38) -> -5.1075138 | H38: =H308 -> 0.011 | I38: =I308 -> -1.077 | J38: =J308 -> -0.84942961 | K38: =K308 -> 0.27859706 | L38: =SUM(H38:K38) -> -1.6368326 | M38: =M308 -> -1.2259987 | N38: =N308 -> -0.798 | O38: =O308 -> -1.1429935 | P38: =P308 -> -1.6297332 | Q38: =SUM(M38:P38) -> -4.7967253 | R38: =R308 -> -2.66 | S38: =S308 -> -2.881 | T38: =T308 -> -3.051 | U38: =U308 -> -3.1921326 | V38: =SUM(R38:U38) -> -11.784133 | W38: =W308 -> -3.534 | X38: =X308 -> -3.937 | Y38: =Y308 -> -5.329 | Z38: =Z308 -> -3.965731 | AA38: =SUM(W38:Z38) -> -16.765731 | AB38: =AB308 -> -7.685 | AC38: =AC308 -> -6.945 | AD38: =AD308 -> -8.5344265 | AE38: =AE308 -> -9.512 | AF38: =SUM(AB38:AE38) -> -32.676427 | AG38: =AG308 -> -10.438 | AH38: =AH308 -> -8.6196586 | AI38: =AI308 -> -9.2383245 | AJ38: =AJ308 -> -11.465266 | AK38: =SUM(AG38:AJ38) -> -39.761249 | AL38: =AL308 -> -46.131487 | AM38: =AM308 -> -52.682328 | AN38: =AN308 -> -57.280853 | AO38: =AO308 -> -61.873279 | AP38: =AP308 -> -66.429598 | AQ38: =AQ308 -> -70.915934 | AR38: =AR308 -> -75.294189 | AS38: =AS308 -> -79.521653 | AT38: =AT308 -> -83.550594 | AU38: x
AU39: x
B40: EBT | C40: =C35+C38 -> 0.246 | D40: =D35+D38 -> -2.663 | E40: =E35+E38 -> 9.407 | F40: =F35+F38 -> 28.368177 | G40: =SUM(C40:F40) -> 35.358177 | H40: =H35+H38 -> 8.559 | I40: =I35+I38 -> 16.652045 | J40: =J35+J38 -> 22.857899 | K40: =K35+K38 -> 40.662161 | L40: =SUM(H40:K40) -> 88.731105 | M40: =M35+M38 -> 27.145797 | N40: =N35+N38 -> 23.688748 | O40: =O35+O38 -> 28.405054 | P40: =P35+P38 -> 41.180789 | Q40: =SUM(M40:P40) -> 120.42039 | R40: =R35+R38 -> 29.301682 | S40: =S35+S38 -> 31.797661 | T40: =T35+T38 -> 31.854373 | U40: =U35+U38 -> 43.975491 | V40: =SUM(R40:U40) -> 136.92921 | W40: =W35+W38 -> 30.78131 | X40: =X35+X38 -> 31.968 | Y40: =Y35+Y38 -> 31.425061 | Z40: =Z35+Z38 -> 53.266342 | AA40: =SUM(W40:Z40) -> 147.44071 | AB40: =AB35+AB38 -> 42.635613 | AC40: =AC35+AC38 -> 42.152 | AD40: =AD35+AD38 -> 38.918229 | AE40: =AE35+AE38 -> 56.072 | AF40: =SUM(AB40:AE40) -> 179.77784 | AG40: =AG35+AG38 -> 43.402 | AH40: =AH35+AH38 -> 46.95144 | AI40: =AI35+AI38 -> 50.449199 | AJ40: =AJ35+AJ38 -> 72.252105 | AK40: =SUM(AG40:AJ40) -> 213.05474 | AL40: =AL35+AL38 -> 251.55993 | AM40: =AM35+AM38 -> 298.25927 | AN40: =AN35+AN38 -> 353.91412 | AO40: =AO35+AO38 -> 417.18012 | AP40: =AP35+AP38 -> 488.74417 | AQ40: =AQ35+AQ38 -> 569.35384 | AR40: =AR35+AR38 -> 659.82007 | AS40: =AS35+AS38 -> 761.02036 | AT40: =AT35+AT38 -> 873.90255 | AU40: x
B41: % margem ebt | C41: =C40/C$16 -> 0.0043823708 | D41: =D40/D$16 -> -0.11364315 | E41: =E40/E$16 -> 0.14195388 | F41: =F40/F$16 -> 0.23351267 | G41: =G40/G16 -> 0.13226934 | H41: =H40/H$16 -> 0.13433679 | I41: =I40/I$16 -> 0.17632594 | J41: =J40/J$16 -> 0.18318411 | K41: =K40/K$16 -> 0.26811601 | L41: =L40/L16 -> 0.20417112 | M41: =M40/M$16 -> 0.24124451 | N41: =N40/N$16 -> 0.18022069 | O41: =O40/O$16 -> 0.2056147 | P41: =P40/P$16 -> 0.22222408 | Q41: =Q40/Q16 -> 0.21222219 | R41: =R40/R$16 -> 0.20680134 | S41: =S40/S$16 -> 0.20412507 | T41: =T40/T$16 -> 0.19390562 | U41: =U40/U$16 -> 0.1981351 | V41: =V40/V16 -> 0.20027964 | W41: =W40/W$16 -> 0.18985456 | X41: =X40/X$16 -> 0.16649827 | Y41: =Y40/Y$16 -> 0.15379187 | Z41: =Z40/Z$16 -> 0.19490705 | AA41: =AA40/AA16 -> 0.17726374 | AB41: =AB40/AB$16 -> 0.20036851 | AC41: =AC40/AC$16 -> 0.17411634 | AD41: =AD40/AD$16 -> 0.1449312 | AE41: =AE40/AE$16 -> 0.17354057 | AF41: =AF40/AF16 -> 0.17178765 | AG41: =AG40/AG$16 -> 0.17280756 | AH41: =AH40/AH$16 -> 0.18020277 | AI41: =AI40/AI$16 -> 0.18338578 | AJ41: =AJ40/AJ$16 -> 0.19663639 | AK41: =AK40/AK16 -> 0.18458369 | AL41: =AL40/AL16 -> 0.19099921 | AM41: =AM40/AM16 -> 0.19910518 | AN41: =AN40/AN16 -> 0.20906295 | AO41: =AO40/AO16 -> 0.21927469 | AP41: =AP40/AP16 -> 0.22967288 | AQ41: =AQ40/AQ16 -> 0.24021109 | AR41: =AR40/AR16 -> 0.25085676 | ... AT41: =AT40/AT16 -> 0.27238418 | AU41: x
AU42: x
B43: (-) IR/CS | C43: -0.812 | D43: 1.284 | E43: -2.543 | F43: -7.4551602 | G43: =SUM(C43:F43) -> -9.5261602 | H43: -1.333 | I43: -3.271 | J43: -1.3892769 | K43: -5.5921098 | L43: =SUM(H43:K43) -> -11.585387 | M43: -7.1686303 | N43: -6.419 | O43: -3.9200337 | P43: -6.453 | Q43: =SUM(M43:P43) -> -23.960664 | R43: -4.2142218 | S43: -4.966 | T43: -4.691 | U43: -8.648 | V43: =SUM(R43:U43) -> -22.519222 | W43: -4.396 | X43: -5.723 | Y43: -6.899678 | Z43: -12.668 | AA43: =SUM(W43:Z43) -> -29.686678 | AB43: -7.845 | AC43: -8.163 | AD43: -9.016 | AE43: -12.436 | AF43: =SUM(AB43:AE43) -> -37.46 | AG43: -9.001 | AH43: =AH478 -> -13.322946 | AI43: =AI478 -> -3.4036637 | AJ43: =AJ478 -> -9.848502 | AK43: =SUM(AG43:AJ43) -> -35.576112 | AL43: =AL478 -> -51.966339 | AM43: =AM478 -> -36.359147 | AN43: =AN478 -> -44.856219 | AO43: =AO478 -> -54.910463 | AP43: =AP478 -> -66.86585 | AQ43: =AQ478 -> -80.898469 | AR43: =AR478 -> -97.203272 | AS43: =AS478 -> -115.99451 | AT43: =AT478 -> -137.50643 | AU43: x
B44: % tax rate | C44: =C43/C40 -> -3.300813 | D44: =D43/D40 -> -0.48216297 | E44: =E43/E40 -> -0.2703306 | F44: =F43/F40 -> -0.26280012 | G44: =G43/G40 -> -0.26941887 | H44: =H43/H40 -> -0.15574249 | I44: =I43/I40 -> -0.19643233 | J44: =J43/J40 -> -0.060778856 | ... AT44: =AT43/AT40 -> -0.15734755 | AU44: x
AU45: x
B46: Lucro líquido | C46: =C40+C43 -> -0.566 | D46: =D40+D43 -> -1.379 | E46: =E40+E43 -> 6.864 | F46: =F40+F43 -> 20.913017 | G46: =SUM(C46:F46) -> 25.832017 | H46: =H40+H43 -> 7.226 | I46: =I40+I43 -> 13.381045 | J46: =J40+J43 -> 21.468622 | K46: =K40+K43 -> 35.070051 | L46: =SUM(H46:K46) -> 77.145718 | M46: =M40+M43 -> 19.977166 | N46: =N40+N43 -> 17.269748 | O46: =O40+O43 -> 24.48502 | P46: =P40+P43 -> 34.727789 | Q46: =SUM(M46:P46) -> 96.459724 | R46: =R40+R43 -> 25.08746 | S46: =S40+S43 -> 26.831661 | T46: =T40+T43 -> 27.163373 | U46: =U40+U43 -> 35.327491 | V46: =SUM(R46:U46) -> 114.40999 | W46: =W40+W43 -> 26.38531 | X46: =X40+X43 -> 26.245 | Y46: =Y40+Y43 -> 24.525383 | Z46: =Z40+Z43 -> 40.598342 | AA46: =SUM(W46:Z46) -> 117.75404 | AB46: =AB40+AB43 -> 34.790613 | AC46: =AC40+AC43 -> 33.989 | AD46: =AD40+AD43 -> 29.902229 | AE46: =AE40+AE43 -> 43.636 | AF46: =SUM(AB46:AE46) -> 142.31784 | AG46: =AG40+AG43 -> 34.401 | AH46: =AH40+AH43 -> 33.628494 | AI46: =AI40+AI43 -> 47.045536 | AJ46: =AJ40+AJ43 -> 62.403603 | AK46: =SUM(AG46:AJ46) -> 177.47863 | AL46: =AL40+AL43 -> 199.59359 | AM46: =AM40+AM43 -> 261.90013 | AN46: =AN40+AN43 -> 309.05791 | AO46: =AO40+AO43 -> 362.26965 | AP46: =AP40+AP43 -> 421.87832 | AQ46: =AQ40+AQ43 -> 488.45537 | AR46: =AR40+AR43 -> 562.61679 | AS46: =AS40+AS43 -> 645.02584 | AT46: =AT40+AT43 -> 736.39613 | AU46: x
B47: % yoy | H47: =H46/C46-1 -> -13.766784 | I47: =I46/D46-1 -> -10.703441 | J47: =J46/E46-1 -> 2.127713 | K47: =K46/F46-1 -> 0.67694845 | L47: =L46/SUM(C46:F46)-1 -> 1.9864381 | M47: =M46/H46-1 -> 1.7646231 | N47: =N46/I46-1 -> 0.29061281 | O47: =O46/J46-1 -> 0.14050266 | P47: =P46/K46-1 -> -0.0097593973 | Q47: =Q46/SUM(H46:K46)-1 -> 0.25035745 | R47: =R46/M46-1 -> 0.25580672 | S47: =S46/N46-1 -> 0.55367993 | T47: =T46/O46-1 -> 0.10938742 | U47: =U46/P46-1 -> 0.017268666 | V47: =V46/SUM(M46:P46)-1 -> 0.18609075 | W47: =W46/R46-1 -> 0.051733009 | X47: =X46/S46-1 -> -0.021864519 | Y47: =Y46/T46-1 -> -0.097115714 | Z47: =Z46/U46-1 -> 0.14919971 | AA47: =AA46/SUM(R46:U46)-1 -> 0.029228649 | AB47: =AB46/W46-1 -> 0.31855996 | AC47: =AC46/X46-1 -> 0.29506573 | AD47: =AD46/Y46-1 -> 0.21923596 | AE47: =AE46/Z46-1 -> 0.074822205 | AF47: =AF46/SUM(W46:Z46)-1 -> 0.20860268 | AG47: =AG46/AB46-1 -> -0.011198789 | AH47: =AH46/AC46-1 -> -0.010606558 | AI47: =AI46/AD46-1 -> 0.573312 | AJ47: =AJ46/AE46-1 -> 0.43009449 | AK47: =AK46/SUM(AB46:AE46)-1 -> 0.24705821 | AL47: =AL46/AK46-1 -> 0.12460631 | AM47: =AM46/AL46-1 -> 0.31216701 | AN47: =AN46/AM46-1 -> 0.18006017 | AO47: =AO46/AN46-1 -> 0.17217404 | AP47: =AP46/AO46-1 -> 0.16454224 | AQ47: =AQ46/AP46-1 -> 0.15781104 | AR47: =AR46/AQ46-1 -> 0.15182845 | AS47: =AS46/AR46-1 -> 0.14647456 | AT47: =AT46/AS46-1 -> 0.14165368 | AU47: x
B48: % margem líquida | C48: =C46/C16 -> -0.010083016 | D48: =D46/D16 -> -0.058848632 | E48: =E46/E16 -> 0.1035794 | F48: =F46/F16 -> 0.17214551 | G48: =G46/G16 -> 0.096633481 | H48: =H46/H16 -> 0.11341484 | I48: =I46/I16 -> 0.14168982 | J48: =J46/J16 -> 0.17205039 | ... AT48: =AT46/AT16 -> 0.2295252 | AU48: x
AU49: x
A50: * | B50: 3 - BP | AU50: x
AU51: x
B52: Ativo | C52: =C53+C59 -> 263.33 | D52: =D53+D59 -> 284.106 | E52: =E53+E59 -> 309.554 | F52: =F53+F59 -> 356.846 | G52: =F52 -> 356.846 | H52: =H53+H59 -> 369.26 | I52: =I53+I59 -> 380.352 | J52: =J53+J59 -> 420.609 | K52: =K53+K59 -> 474.906 | L52: =K52 -> 474.906 | M52: =M53+M59 -> 484.299 | N52: =N53+N59 -> 500.839 | O52: =O53+O59 -> 517.058 | P52: =P53+P59 -> 579.859 | Q52: =P52 -> 579.859 | R52: =R53+R59 -> 587.342 | S52: =S53+S59 -> 594.833 | T52: =T53+T59 -> 621.261 | U52: =U53+U59 -> 682.102 | V52: =U52 -> 682.102 | W52: =W53+W59 -> 696.285 | X52: =X53+X59 -> 706.394 | Y52: =Y53+Y59 -> 728.862 | Z52: =Z53+Z59 -> 825.166 | AA52: =Z52 -> 825.166 | AB52: =AB53+AB59 -> 829.401 | AC52: =AC53+AC59 -> 822.781 | AD52: =AD53+AD59 -> 901.331 | AE52: =AE53+AE59 -> 974.206 | AF52: =AE52 -> 974.206 | AG52: =AG53+AG59 -> 1003.133 | AH52: =AH53+AH59 -> 1012.6063 | AI52: =AI53+AI59 -> 1051.4644 | AJ52: =AJ53+AJ59 -> 1130.0686 | AK52: =AJ52 -> 1130.0686 | AL52: =AL53+AL59 -> 1288.1377 | AM52: =AM53+AM59 -> 1460.9192 | AN52: =AN53+AN59 -> 1646.3929 | AO52: =AO53+AO59 -> 1845.5391 | AP52: =AP53+AP59 -> 2059.3661 | AQ52: =AQ53+AQ59 -> 2288.9188 | AR52: =AR53+AR59 -> 2535.2852 | AS52: =AS53+AS59 -> 2799.6027 | AT52: =AT53+AT59 -> 3083.0638 | AU52: x
B53: Ativo Circulante | C53: =SUM(C54:C58) -> 174.942 | D53: =SUM(D54:D58) -> 194.397 | E53: =SUM(E54:E58) -> 221.454 | F53: =SUM(F54:F58) -> 281.105 | G53: =F53 -> 281.105 | H53: =SUM(H54:H58) -> 277.583 | I53: =SUM(I54:I58) -> 283.43 | J53: =SUM(J54:J58) -> 325.904 | K53: =SUM(K54:K58) -> 367.031 | L53: =K53 -> 367.031 | M53: =SUM(M54:M58) -> 369.247 | N53: =SUM(N54:N58) -> 373.495 | O53: =SUM(O54:O58) -> 374.537 | P53: =SUM(P54:P58) -> 427.793 | Q53: =P53 -> 427.793 | R53: =SUM(R54:R58) -> 429.871 | S53: =SUM(S54:S58) -> 426.288 | T53: =SUM(T54:T58) -> 441.568 | U53: =SUM(U54:U58) -> 502.705 | V53: =U53 -> 502.705 | W53: =SUM(W54:W58) -> 507.967 | X53: =SUM(X54:X58) -> 500.149 | Y53: =SUM(Y54:Y58) -> 512.009 | Z53: =SUM(Z54:Z58) -> 568.521 | AA53: =Z53 -> 568.521 | AB53: =SUM(AB54:AB58) -> 572.265 | AC53: =SUM(AC54:AC58) -> 562.662 | AD53: =SUM(AD54:AD58) -> 612.629 | AE53: =SUM(AE54:AE58) -> 681.166 | AF53: =AE53 -> 681.166 | AG53: =SUM(AG54:AG58) -> 696.965 | AH53: =SUM(AH54:AH58) -> 699.35365 | AI53: =SUM(AI54:AI58) -> 715.88375 | AJ53: =SUM(AJ54:AJ58) -> 779.05291 | AK53: =AJ53 -> 779.05291 | AL53: =SUM(AL54:AL58) -> 876.07325 | AM53: =SUM(AM54:AM58) -> 983.8766 | AN53: =SUM(AN54:AN58) -> 1099.9831 | AO53: =SUM(AO54:AO58) -> 1224.9236 | AP53: =SUM(AP54:AP58) -> 1359.2599 | AQ53: =SUM(AQ54:AQ58) -> 1503.5864 | AR53: =SUM(AR54:AR58) -> 1658.5316 | AS53: =SUM(AS54:AS58) -> 1824.7606 | AT53: =SUM(AT54:AT58) -> 2002.9767 | AU53: x
B54: Caixa | C54: 74.395 | D54: 86.768 | E54: 77.26 | F54: 89.077 | G54: =F54 -> 89.077 | H54: 85.998 | I54: 63.422 | J54: 63.2 | K54: 66.771 | L54: =K54 -> 66.771 | M54: 74.359 | N54: 60.671 | O54: 53.347 | P54: 60.489 | Q54: =P54 -> 60.489 | R54: 63.286 | S54: 39.929 | T54: 46.274 | U54: 54.477 | V54: =U54 -> 54.477 | W54: 82.179 | X54: 66.988 | Y54: 47.357 | Z54: 23.41 | AA54: =Z54 -> 23.41 | AB54: 50.44 | AC54: 23.674 | AD54: 20.658 | AE54: 35.255 | AF54: =AE54 -> 35.255 | AG54: 63.637 | AH54: =AH126 -> 63.637 | AI54: =AI126 -> 63.637 | AJ54: =AJ126 -> 63.637 | AK54: =AJ54 -> 63.637 | AL54: =AL126 -> 63.637 | AM54: =AM126 -> 63.637 | AN54: =AN126 -> 63.637 | AO54: =AO126 -> 63.637 | AP54: =AP126 -> 63.637 | AQ54: =AQ126 -> 63.637 | AR54: =AR126 -> 63.637 | AS54: =AS126 -> 63.637 | AT54: =AT126 -> 63.637 | AU54: x
B55: Contas a receber | C55: 18.665 | D55: 30.469 | E55: 51.711 | F55: 98.981 | G55: =F55 -> 98.981 | H55: 56.056 | I55: 70.374 | J55: 92.999 | K55: 125.322 | L55: =K55 -> 125.322 | M55: 84.68 | N55: 92.551 | O55: 98.753 | P55: 152.769 | Q55: =P55 -> 152.769 | R55: 115.381 | S55: 117.827 | T55: 126.392 | U55: 196.536 | V55: =U55 -> 196.536 | W55: 148.743 | X55: 152.949 | Y55: 147.733 | Z55: 241.664 | AA55: =Z55 -> 241.664 | AB55: 173.739 | AC55: 176.615 | AD55: 206.108 | AE55: 286.622 | AF55: =AE55 -> 286.622 | AG55: 221.457 | AH55: =AH291 -> 208.97149 | AI55: =AI291 -> 229.51955 | AJ55: =AJ291 -> 316.12818 | AK55: =AJ55 -> 316.12818 | AL55: =AL291 -> 360.72413 | AM55: =AM291 -> 410.27656 | AN55: =AN291 -> 463.64558 | AO55: =AO291 -> 521.07521 | AP55: =AP291 -> 582.82366 | AQ55: =AQ291 -> 649.16412 | AR55: =AR291 -> 720.38559 | AS55: =AS291 -> 796.79372 | AT55: =AT291 -> 878.71175 | AU55: x
B56: Estoques | C56: 64.084 | D56: 61.258 | E56: 77.718 | F56: 79.901 | G56: =F56 -> 79.901 | H56: 115.821 | I56: 133.538 | J56: 148.202 | K56: 158.638 | L56: =K56 -> 158.638 | M56: 197.631 | N56: 207.751 | O56: 212.129 | P56: 204.466 | Q56: =P56 -> 204.466 | R56: 240.17 | S56: 253.857 | T56: 254.425 | U56: 232.856 | V56: =U56 -> 232.856 | W56: 253.506 | X56: 260.537 | Y56: 296.402 | Z56: 289.396 | AA56: =Z56 -> 289.396 | AB56: 328.488 | AC56: 337.287 | AD56: 354.764 | AE56: 336.936 | AF56: =AE56 -> 336.936 | AG56: 384.205 | AH56: =AH294 -> 399.07916 | AI56: =AI294 -> 395.0612 | AJ56: =AJ294 -> 371.62173 | AK56: =AJ56 -> 371.62173 | AL56: =AL294 -> 424.04612 | AM56: =AM294 -> 482.29704 | AN56: =AN294 -> 545.03453 | AO56: =AO294 -> 612.54543 | AP56: =AP294 -> 685.13329 | AQ56: =AQ294 -> 763.11924 | AR56: =AR294 -> 846.84302 | AS56: =AS294 -> 936.66393 | AT56: =AT294 -> 1032.962 | AU56: x
B57: Impostos a recuperar | C57: 13.407 | D57: 11.49 | E57: 9.073 | F57: 11.523 | G57: =F57 -> 11.523 | H57: 16.54 | I57: 14.124 | J57: 18.123 | K57: 13.263 | L57: =K57 -> 13.263 | M57: 8.856 | N57: 8.922 | O57: 5.926 | P57: 4.938 | Q57: =P57 -> 4.938 | R57: 4.962 | S57: 6.034 | T57: 6.349 | U57: 10.336 | V57: =U57 -> 10.336 | W57: 10.915 | X57: 4.359 | Y57: 4.188 | Z57: 4.281 | AA57: =Z57 -> 4.281 | AB57: 4.875 | AC57: 4.941 | AD57: 9.864 | AE57: 6.057 | AF57: =AE57 -> 6.057 | AG57: 6.612 | AH57: =AG57 -> 6.612 | AI57: =AH57 -> 6.612 | AJ57: =AI57 -> 6.612 | AK57: =AJ57 -> 6.612 | AL57: =AK57 -> 6.612 | AM57: =AL57 -> 6.612 | AN57: =AM57 -> 6.612 | AO57: =AN57 -> 6.612 | ... AT57: =AS57 -> 6.612 | AU57: x
B58: Outros créditos | C58: 4.391 | D58: 4.412 | E58: 5.692 | F58: 1.623 | G58: =F58 -> 1.623 | H58: 3.168 | I58: 1.972 | J58: 3.38 | K58: 3.037 | L58: =K58 -> 3.037 | M58: 3.721 | N58: 3.6 | O58: 4.382 | P58: 5.131 | Q58: =P58 -> 5.131 | R58: 6.072 | S58: 8.641 | T58: 8.128 | U58: 8.5 | V58: =U58 -> 8.5 | W58: 12.624 | X58: 15.316 | Y58: 16.329 | Z58: 9.77 | AA58: =Z58 -> 9.77 | AB58: 14.723 | AC58: 20.145 | AD58: 21.235 | AE58: 16.296 | AF58: =AE58 -> 16.296 | AG58: 21.054 | AH58: =AG58 -> 21.054 | AI58: =AH58 -> 21.054 | AJ58: =AI58 -> 21.054 | AK58: =AJ58 -> 21.054 | AL58: =AK58 -> 21.054 | AM58: =AL58 -> 21.054 | AN58: =AM58 -> 21.054 | AO58: =AN58 -> 21.054 | ... AT58: =AS58 -> 21.054 | AU58: x
B59: Ativo Não Circulante | C59: =SUM(C60:C66) -> 88.388 | D59: =SUM(D60:D66) -> 89.709 | E59: =SUM(E60:E66) -> 88.1 | F59: =SUM(F60:F66) -> 75.741 | G59: =F59 -> 75.741 | H59: =SUM(H60:H66) -> 91.677 | I59: =SUM(I60:I66) -> 96.922 | J59: =SUM(J60:J66) -> 94.705 | K59: =SUM(K60:K66) -> 107.875 | L59: =K59 -> 107.875 | M59: =SUM(M60:M66) -> 115.052 | N59: =SUM(N60:N66) -> 127.344 | O59: =SUM(O60:O66) -> 142.521 | P59: =SUM(P60:P66) -> 152.066 | Q59: =P59 -> 152.066 | R59: =SUM(R60:R66) -> 157.471 | S59: =SUM(S60:S66) -> 168.545 | T59: =SUM(T60:T66) -> 179.693 | U59: =SUM(U60:U66) -> 179.397 | V59: =U59 -> 179.397 | W59: =SUM(W60:W66) -> 188.318 | X59: =SUM(X60:X66) -> 206.245 | Y59: =SUM(Y60:Y66) -> 216.853 | Z59: =SUM(Z60:Z66) -> 256.645 | AA59: =Z59 -> 256.645 | AB59: =SUM(AB60:AB66) -> 257.136 | AC59: =SUM(AC60:AC66) -> 260.119 | AD59: =SUM(AD60:AD66) -> 288.702 | AE59: =SUM(AE60:AE66) -> 293.04 | AF59: =AE59 -> 293.04 | AG59: =SUM(AG60:AG66) -> 306.168 | AH59: =SUM(AH60:AH66) -> 313.25268 | AI59: =SUM(AI60:AI66) -> 335.58063 | AJ59: =SUM(AJ60:AJ66) -> 351.0157 | AK59: =AJ59 -> 351.0157 | AL59: =SUM(AL60:AL66) -> 412.06442 | AM59: =SUM(AM60:AM66) -> 477.0426 | AN59: =SUM(AN60:AN66) -> 546.40984 | AO59: =SUM(AO60:AO66) -> 620.61545 | AP59: =SUM(AP60:AP66) -> 700.10617 | AQ59: =SUM(AQ60:AQ66) -> 785.33245 | AR59: =SUM(AR60:AR66) -> 876.75358 | AS59: =SUM(AS60:AS66) -> 974.84201 | AT59: =SUM(AT60:AT66) -> 1080.0871 | AU59: x
B60: Depósitos judiciais | C60: 11.378 | D60: 11.638 | E60: 11.894 | F60: 1.103 | G60: =F60 -> 1.103 | H60: 0.946 | I60: 0.942 | J60: 0.947 | K60: 1.274 | L60: =K60 -> 1.274 | M60: 0.676 | N60: 0.694 | O60: 0.4 | P60: 0.41 | Q60: =P60 -> 0.41 | R60: 0.512 | S60: 0.467 | T60: 0.474 | U60: 0.445 | V60: =U60 -> 0.445 | W60: 0.62 | X60: 2.571 | Y60: 2.863 | Z60: 2.999 | AA60: =Z60 -> 2.999 | AB60: 3.092 | AC60: 3.205 | AD60: 3.258 | AE60: 3.37 | AF60: =AE60 -> 3.37 | AG60: 3.486 | AH60: =AG60 -> 3.486 | AI60: =AH60 -> 3.486 | AJ60: =AI60 -> 3.486 | AK60: =AJ60 -> 3.486 | AL60: =AK60 -> 3.486 | AM60: =AL60 -> 3.486 | AN60: =AM60 -> 3.486 | AO60: =AN60 -> 3.486 | ... AT60: =AS60 -> 3.486 | AU60: x
B61: Contas a receber partes rel. | C61: 0 | D61: 0 | E61: 0 | F61: 0 | G61: =F61 -> 0 | H61: 0 | I61: 0 | J61: 0 | K61: 0 | L61: =K61 -> 0 | M61: 0 | N61: 0 | O61: 0 | P61: 0 | Q61: =P61 -> 0 | R61: 0 | S61: 0 | T61: 0 | U61: 0 | V61: =U61 -> 0 | W61: 0 | X61: 0 | Y61: 0 | Z61: 0 | AA61: =Z61 -> 0 | AB61: 0 | AC61: 0 | AD61: 0 | AE61: 0 | AF61: =AE61 -> 0 | AG61: 0 | AH61: =AG61 -> 0 | AI61: =AH61 -> 0 | AJ61: =AI61 -> 0 | AK61: =AJ61 -> 0 | AL61: =AK61 -> 0 | AM61: =AL61 -> 0 | AN61: =AM61 -> 0 | AO61: =AN61 -> 0 | ... AT61: =AS61 -> 0 | AU61: x
B62: IR/CS diferidos | C62: 4.499 | D62: 6.662 | E62: 5.642 | F62: 4.179 | G62: =F62 -> 4.179 | H62: 4.48 | I62: 4.384 | J62: 4.388 | K62: 7.277 | L62: =K62 -> 7.277 | M62: 6.826 | N62: 6.594 | O62: 8.594 | P62: 8.422 | Q62: =P62 -> 8.422 | R62: 8.354 | S62: 8.163 | T62: 7.883 | U62: 6.4 | V62: =U62 -> 6.4 | W62: 6.178 | X62: 5.911 | Y62: 5.354 | Z62: 4.398 | AA62: =Z62 -> 4.398 | AB62: 4.873 | AC62: 5.02 | AD62: 5.519 | AE62: 5.788 | AF62: =AE62 -> 5.788 | AG62: 6.214 | AH62: =AG62 -> 6.214 | AI62: =AH62 -> 6.214 | AJ62: =AI62 -> 6.214 | AK62: =AJ62 -> 6.214 | AL62: =AK62 -> 6.214 | AM62: =AL62 -> 6.214 | AN62: =AM62 -> 6.214 | AO62: =AN62 -> 6.214 | ... AT62: =AS62 -> 6.214 | AU62: x
B63: Impostos a recuperar | C63: 16.091 | D63: 17.755 | E63: 17.809 | F63: 12.812 | G63: =F63 -> 12.812 | H63: 6.678 | I63: 6.122 | J63: 0.374 | K63: 4.225 | L63: =K63 -> 4.225 | M63: 4.455 | N63: 6.373 | O63: 7.854 | P63: 7.833 | Q63: =P63 -> 7.833 | R63: 9.426 | S63: 8.847 | T63: 10.79 | U63: 5.256 | V63: =U63 -> 5.256 | W63: 5.2 | X63: 3.988 | Y63: 4.401 | Z63: 5.014 | AA63: =Z63 -> 5.014 | AB63: 5.223 | AC63: 3.287 | AD63: 3.065 | AE63: 3.334 | AF63: =AE63 -> 3.334 | AG63: 2.922 | AH63: =AG63 -> 2.922 | AI63: =AH63 -> 2.922 | AJ63: =AI63 -> 2.922 | AK63: =AJ63 -> 2.922 | AL63: =AK63 -> 2.922 | AM63: =AL63 -> 2.922 | AN63: =AM63 -> 2.922 | AO63: =AN63 -> 2.922 | ... AT63: =AS63 -> 2.922 | AU63: x
B64: Direito de uso | C64: 44.853 | D64: 42.849 | E64: 42.325 | F64: 46.948 | G64: =F64 -> 46.948 | H64: 67.183 | I64: 69.616 | J64: 71.162 | K64: 73.89 | L64: =K64 -> 73.89 | M64: 78.175 | N64: 77.881 | O64: 81.371 | P64: 84.322 | Q64: =P64 -> 84.322 | R64: 83.347 | S64: 90.228 | T64: 92.237 | U64: 93.983 | V64: =U64 -> 93.983 | W64: 95.634 | X64: 107.056 | Y64: 109.569 | Z64: 142.771 | AA64: =Z64 -> 142.771 | AB64: 137.636 | AC64: 136.772 | AD64: 160.678 | AE64: 162.353 | AF64: =AE64 -> 162.353 | AG64: 169.086 | AH64: =AH346 -> 169.086 | AI64: =AI346 -> 184.04935 | AJ64: =AJ346 -> 188.73536 | AK64: =AJ64 -> 188.73536 | AL64: =AL346 -> 217.35008 | AM64: =AM346 -> 248.35443 | AN64: =AN346 -> 281.91584 | AO64: =AO346 -> 318.2125 | AP64: =AP346 -> 357.43404 | AQ64: =AQ346 -> 399.78221 | AR64: =AR346 -> 445.4716 | AS64: =AS346 -> 494.73048 | AT64: =AT346 -> 547.80157 | AU64: x
B65: Imobilizado | C65: 9.81 | D65: 9.19 | E65: 8.956 | F65: 9.2478 | G65: =F65 -> 9.2478 | H65: 10.589 | I65: 13.346 | J65: 14.095 | K65: 16.234 | L65: =K65 -> 16.234 | M65: 18.958 | N65: 28.923 | O65: 34.936 | P65: 40.131 | Q65: =P65 -> 40.131 | R65: 42.781 | S65: 46.188 | T65: 48.481 | U65: 52.627 | V65: =U65 -> 52.627 | W65: 56.291 | X65: 62.217 | Y65: 68.711 | Z65: 76.443 | AA65: =Z65 -> 76.443 | AB65: 80.053 | AC65: 83.288 | AD65: 85.789 | AE65: 93.733 | AF65: =AE65 -> 93.733 | AG65: 97.552 | AH65: =AH421 -> 103.91476 | AI65: =AI421 -> 110.46247 | AJ65: =AJ421 -> 119.52841 | AK65: =AJ65 -> 119.52841 | AL65: =AL421 -> 146.15952 | AM65: =AM421 -> 174.03211 | AN65: =AN421 -> 203.37086 | AO65: =AO421 -> 234.38953 | AP65: =AP421 -> 267.2945 | AQ65: =AQ421 -> 302.28769 | AR65: =AR421 -> 339.56915 | AS65: =AS421 -> 379.33923 | AT65: =AT421 -> 421.80056 | AU65: x
B66: Intangível | C66: 1.757 | D66: 1.615 | E66: 1.474 | F66: 1.4512 | G66: =F66 -> 1.4512 | H66: 1.801 | I66: 2.512 | J66: 3.739 | K66: 4.975 | L66: =K66 -> 4.975 | M66: 5.962 | N66: 6.879 | O66: 9.366 | P66: 10.948 | Q66: =P66 -> 10.948 | R66: 13.051 | S66: 14.652 | T66: 19.828 | U66: 20.686 | V66: =U66 -> 20.686 | W66: 24.395 | X66: 24.502 | Y66: 25.955 | Z66: 25.02 | AA66: =Z66 -> 25.02 | AB66: 26.259 | AC66: 28.547 | AD66: 30.393 | AE66: 24.462 | AF66: =AE66 -> 24.462 | AG66: 26.908 | AH66: =AH447 -> 27.629918 | AI66: =AI447 -> 28.446811 | AJ66: =AJ447 -> 30.129936 | AK66: =AJ66 -> 30.129936 | AL66: =AL447 -> 35.932827 | AM66: =AM447 -> 42.034054 | AN66: =AN447 -> 48.501144 | AO66: =AO447 -> 55.391417 | AP66: =AP447 -> 62.755628 | AQ66: =AQ447 -> 70.640555 | AR66: =AR447 -> 79.090835 | AS66: =AS447 -> 88.150297 | AT66: =AT447 -> 97.862923 | AU66: x
AU67: x
B68: Passivo | C68: =C69+C78+C83 -> 263.33 | D68: =D69+D78+D83 -> 284.106 | E68: =E69+E78+E83 -> 309.554 | F68: =F69+F78+F83 -> 356.846 | G68: =F68 -> 356.846 | H68: =H69+H78+H83 -> 369.26 | I68: =I69+I78+I83 -> 380.352 | J68: =J69+J78+J83 -> 420.609 | K68: =K69+K78+K83 -> 474.906 | L68: =K68 -> 474.906 | M68: =M69+M78+M83 -> 484.299 | N68: =N69+N78+N83 -> 500.839 | O68: =O69+O78+O83 -> 517.058 | P68: =P69+P78+P83 -> 579.859 | Q68: =P68 -> 579.859 | R68: =R69+R78+R83 -> 587.342 | S68: =S69+S78+S83 -> 594.833 | T68: =T69+T78+T83 -> 621.261 | U68: =U69+U78+U83 -> 682.102 | V68: =U68 -> 682.102 | W68: =W69+W78+W83 -> 696.285 | X68: =X69+X78+X83 -> 706.394 | Y68: =Y69+Y78+Y83 -> 728.862 | Z68: =Z69+Z78+Z83 -> 825.166 | AA68: =Z68 -> 825.166 | AB68: =AB69+AB78+AB83 -> 829.401 | AC68: =AC69+AC78+AC83 -> 822.781 | AD68: =AD69+AD78+AD83 -> 901.33075 | AE68: =AE69+AE78+AE83 -> 974.206 | AF68: =AE68 -> 974.206 | AG68: =AG69+AG78+AG83 -> 1003.133 | AH68: =AH69+AH78+AH83 -> 1012.6063 | AI68: =AI69+AI78+AI83 -> 1051.4644 | AJ68: =AJ69+AJ78+AJ83 -> 1130.0686 | AK68: =AJ68 -> 1130.0686 | AL68: =AL69+AL78+AL83 -> 1288.1377 | AM68: =AM69+AM78+AM83 -> 1460.9192 | AN68: =AN69+AN78+AN83 -> 1646.3929 | AO68: =AO69+AO78+AO83 -> 1845.5391 | AP68: =AP69+AP78+AP83 -> 2059.3661 | AQ68: =AQ69+AQ78+AQ83 -> 2288.9188 | AR68: =AR69+AR78+AR83 -> 2535.2852 | AS68: =AS69+AS78+AS83 -> 2799.6027 | AT68: =AT69+AT78+AT83 -> 3083.0638 | AU68: x
B69: Passivo Circulante | C69: =SUM(C70:C77) -> 186.524 | D69: =SUM(D70:D77) -> 181.841 | E69: =SUM(E70:E77) -> 204.874 | F69: =SUM(F70:F77) -> 99.9358 | G69: =F69 -> 99.9358 | H69: =SUM(H70:H77) -> 86.046 | I69: =SUM(I70:I77) -> 81.742 | J69: =SUM(J70:J77) -> 97.393 | K69: =SUM(K70:K77) -> 128.045 | L69: =K69 -> 128.045 | M69: =SUM(M70:M77) -> 115.252 | N69: =SUM(N70:N77) -> 112.993 | O69: =SUM(O70:O77) -> 114.432 | P69: =SUM(P70:P77) -> 166.436 | Q69: =P69 -> 166.436 | R69: =SUM(R70:R77) -> 155.61 | S69: =SUM(S70:S77) -> 135.318 | T69: =SUM(T70:T77) -> 140.129 | U69: =SUM(U70:U77) -> 177.724 | V69: =U69 -> 177.724 | W69: =SUM(W70:W77) -> 169.149 | X69: =SUM(X70:X77) -> 154.61 | Y69: =SUM(Y70:Y77) -> 168.938 | Z69: =SUM(Z70:Z77) -> 212.423 | AA69: =Z69 -> 212.423 | AB69: =SUM(AB70:AB77) -> 210.341 | AC69: =SUM(AC70:AC77) -> 176.691 | AD69: =SUM(AD70:AD77) -> 214.31675 | AE69: =SUM(AE70:AE77) -> 249.181 | AF69: =AE69 -> 249.181 | AG69: =SUM(AG70:AG77) -> 246.546 | AH69: =SUM(AH70:AH77) -> 401.75153 | AI69: =SUM(AI70:AI77) -> 431.67989 | AJ69: =SUM(AJ70:AJ77) -> 447.88051 | AK69: =AJ69 -> 447.88051 | AL69: =SUM(AL70:AL77) -> 500.13401 | AM69: =SUM(AM70:AM77) -> 557.40439 | AN69: =SUM(AN70:AN77) -> 619.25488 | AO69: =SUM(AO70:AO77) -> 685.99301 | AP69: =SUM(AP70:AP77) -> 757.94528 | AQ69: =SUM(AQ70:AQ77) -> 835.45824 | AR69: =SUM(AR70:AR77) -> 918.89968 | AS69: =SUM(AS70:AS77) -> 1008.6599 | AT69: =SUM(AT70:AT77) -> 1105.1529 | AU69: x
B70: Fornecedores | C70: 22.198 | D70: 12.382 | E70: 29.923 | F70: 36.251 | G70: =F70 -> 36.251 | H70: 38.613 | I70: 32.985 | J70: 37.236 | K70: 41.409 | L70: =K70 -> 41.409 | M70: 46.102 | N70: 51.309 | O70: 38.466 | P70: 60.336 | Q70: =P70 -> 60.336 | R70: 59.483 | S70: 55.844 | T70: 47.986 | U70: 59.198 | V70: =U70 -> 59.198 | W70: 64.033 | X70: 69.998 | Y70: 73.1 | Z70: 81.347 | AA70: =Z70 -> 81.347 | AB70: 75.78 | AC70: 73.773 | AD70: 90.145 | AE70: 88.097 | AF70: =AE70 -> 88.097 | AG70: 80.475 | AH70: =AH297 -> 87.288473 | AI70: =AI297 -> 100.38446 | AJ70: =AJ297 -> 97.166107 | AK70: =AJ70 -> 97.166107 | AL70: =AL297 -> 110.87325 | AM70: =AM297 -> 126.10384 | AN70: =AN297 -> 142.5075 | AO70: =AO297 -> 160.15924 | AP70: =AP297 -> 179.13843 | AQ70: =AQ297 -> 199.52904 | AR70: =AR297 -> 221.41988 | AS70: =AS297 -> 244.90491 | AT70: =AT297 -> 270.08349 | AU70: x
B71: Dívida | C71: 0 | D71: 10.118 | E71: 15.913 | F71: 0 | G71: =F71 -> 0 | H71: 0 | I71: 0 | J71: 0 | K71: 0 | L71: =K71 -> 0 | M71: 0 | N71: 0 | O71: 0 | P71: 0 | Q71: =P71 -> 0 | R71: 0 | S71: 0 | T71: 0 | U71: 0 | V71: =U71 -> 0 | W71: 0 | X71: 0 | Y71: 0 | Z71: 0 | AA71: =Z71 -> 0 | AB71: 0 | AC71: 0 | AD71: 0 | AE71: 0 | AF71: =AE71 -> 0 | AG71: 0 | AH71: =AH128 -> 10 | AI71: =AI128 -> 20 | AJ71: =AJ128 -> 35.636814 | AK71: =AJ71 -> 35.636814 | AL71: =AL128 -> 54.509814 | AM71: =AM128 -> 54.509814 | AN71: =AN128 -> 54.509814 | AO71: =AO128 -> 54.509814 | AP71: =AP128 -> 54.509814 | AQ71: =AQ128 -> 54.509814 | AR71: =AR128 -> 54.509814 | AS71: =AS128 -> 54.509814 | AT71: =AT128 -> 54.509814 | AU71: x
B72: Partes relacionadas | C72: 2.541 | D72: 2.29 | E72: 1.99 | F72: 0.229 | G72: =F72 -> 0.229 | H72: 0.014 | I72: 0 | J72: 0 | K72: 0 | L72: =K72 -> 0 | M72: 0 | N72: 0 | O72: 0 | P72: 0 | Q72: =P72 -> 0 | R72: 0 | S72: 0 | T72: 0 | U72: 0 | V72: =U72 -> 0 | W72: 0 | X72: 0 | Y72: 0 | Z72: 0 | AA72: =Z72 -> 0 | AB72: 0 | AC72: 0 | AD72: 0 | AE72: 0 | AF72: =AE72 -> 0 | AG72: 0 | AH72: =AG72 -> 0 | AI72: =AH72 -> 0 | AJ72: =AI72 -> 0 | AK72: =AJ72 -> 0 | AL72: =AK72 -> 0 | AM72: =AL72 -> 0 | AN72: =AM72 -> 0 | AO72: =AN72 -> 0 | ... AT72: =AS72 -> 0 | AU72: x
B73: Obrigações trabalhistas e prev. | C73: 12.465 | D73: 12.659 | E73: 13.996 | F73: 12.826 | G73: =F73 -> 12.826 | H73: 10.292 | I73: 13.299 | J73: 17.765 | K73: 22.284 | L73: =K73 -> 22.284 | M73: 17.624 | N73: 19.429 | O73: 23.274 | P73: 27.388 | Q73: =P73 -> 27.388 | R73: 23.165 | S73: 24.743 | T73: 29.696 | U73: 34.652 | V73: =U73 -> 34.652 | W73: 32.214 | X73: 29.14 | Y73: 34.768 | Z73: 40.599 | AA73: =Z73 -> 40.599 | AB73: 40.607 | AC73: 35.666 | AD73: 44.505 | AE73: 53.763 | AF73: =AE73 -> 53.763 | AG73: 53.737 | AH73: =AH300 -> 42.200136 | AI73: =AI300 -> 49.560268 | AJ73: =AJ300 -> 59.297609 | AK73: =AJ73 -> 59.297609 | AL73: =AL300 -> 67.662676 | AM73: =AM300 -> 76.957451 | AN73: =AN300 -> 86.968123 | AO73: =AO300 -> 97.740461 | AP73: =AP300 -> 109.3229 | AQ73: =AQ300 -> 121.76668 | AR73: =AR300 -> 135.12602 | AS73: =AS300 -> 149.45824 | AT73: =AT300 -> 164.82398 | AU73: x
B74: Obrigações tributárias | C74: 6.195 | D74: 7.334 | E74: 7.718 | F74: 18.199 | G74: =F74 -> 18.199 | H74: 4.718 | I74: 7.008 | J74: 12.641 | K74: 22.526 | L74: =K74 -> 22.526 | M74: 10.947 | N74: 12.06 | O74: 15.759 | P74: 30.192 | Q74: =P74 -> 30.192 | R74: 11.438 | S74: 12.76 | T74: 17.653 | U74: 30.636 | V74: =U74 -> 30.636 | W74: 15.674 | X74: 14.468 | Y74: 15.554 | Z74: 34.725 | AA74: =Z74 -> 34.725 | AB74: 22.701 | AC74: 18.949 | AD74: 24.77 | AE74: 44.503 | AF74: =AE74 -> 44.503 | AG74: 27.316 | AH74: =AG74 -> 27.316 | AI74: =AH74 -> 27.316 | AJ74: =AI74 -> 27.316 | AK74: =AJ74 -> 27.316 | AL74: =AK74 -> 27.316 | AM74: =AL74 -> 27.316 | AN74: =AM74 -> 27.316 | AO74: =AN74 -> 27.316 | ... AT74: =AS74 -> 27.316 | AU74: x
B75: Arrendamento | C75: 4.847 | D75: 7.404 | E75: 5.631 | F75: 6.9096 | G75: =F75 -> 6.9096 | H75: 8.6515334 | I75: 10.099888 | J75: 10.754483 | K75: 10.429487 | L75: =K75 -> 10.429487 | M75: 12.00064 | N75: 12.802914 | O75: 14.629199 | P75: 15.767496 | Q75: =P75 -> 15.767496 | R75: 16.352981 | S75: 17.213134 | T75: 18.994059 | U75: 17.682221 | V75: =U75 -> 17.682221 | W75: 16.465425 | X75: 16.800515 | Y75: 17.316923 | Z75: 15.889569 | AA75: =Z75 -> 15.889569 | AB75: 16.532386 | AC75: 16.624723 | AD75: 17.897754 | AE75: 17.003553 | AF75: =AE75 -> 17.003553 | AG75: 17.922679 | AH75: =AH360 -> 178.83668 | AI75: =AI360 -> 193.80002 | AJ75: =AJ360 -> 198.48604 | AK75: =AJ75 -> 198.48604 | AL75: =AL360 -> 227.10076 | AM75: =AM360 -> 258.10511 | AN75: =AN360 -> 291.66652 | AO75: =AO360 -> 327.96318 | AP75: =AP360 -> 367.18472 | AQ75: =AQ360 -> 409.53289 | AR75: =AR360 -> 455.22228 | AS75: =AS360 -> 504.48116 | AT75: =AT360 -> 557.55225 | AU75: x
B76: Dividendos e JSCP a pagar | C76: 123.295 | D76: 114.064 | E76: 114.064 | F76: 6.135 | G76: =F76 -> 6.135 | H76: 6.135 | I76: 0 | J76: 0 | K76: 9.881 | L76: =K76 -> 9.881 | M76: 9.881 | N76: 0 | O76: 8.65 | P76: 23.683 | Q76: =P76 -> 23.683 | R76: 27.107 | S76: 10.389 | T76: 15.572 | U76: 27.473 | V76: =U76 -> 27.473 | W76: 33.113 | X76: 12.327 | Y76: 18.304 | Z76: 28.776 | AA76: =Z76 -> 28.776 | AB76: 36.221 | AC76: 17.11 | AD76: 26.451 | AE76: 35.746 | AF76: =AE76 -> 35.746 | AG76: 48.873 | AH76: =AH129 -> 38.873 | AI76: =AI129 -> 28.873 | AJ76: =AJ129 -> 18.873 | AK76: =AJ76 -> 18.873 | AL76: =AL129 -> 0 | AM76: =AM129 -> 0 | AN76: =AN129 -> 0 | AO76: =AO129 -> 0 | AP76: =AP129 -> 0 | AQ76: =AQ129 -> 0 | AR76: =AR129 -> 0 | AS76: =AS129 -> 0 | AT76: =AT129 -> 0 | AU76: x
B77: Outras obrigações | C77: 14.983 | D77: 15.59 | E77: 15.639 | F77: 19.3862 | G77: =F77 -> 19.3862 | H77: 17.622467 | I77: 18.350112 | J77: 18.996517 | K77: 21.515513 | L77: =K77 -> 21.515513 | M77: 18.69736 | N77: 17.392086 | O77: 13.653801 | P77: 9.0695042 | Q77: =P77 -> 9.0695042 | R77: 18.064019 | S77: 14.368866 | T77: 10.227941 | U77: 8.082779 | V77: =U77 -> 8.082779 | W77: 7.6495747 | X77: 11.876485 | Y77: 9.8950771 | Z77: 11.086431 | AA77: =Z77 -> 11.086431 | AB77: 18.499614 | AC77: 14.568277 | AD77: 10.548 | AE77: 10.068447 | AF77: =AE77 -> 10.068447 | AG77: 18.222321 | AH77: =AH303 -> 17.237237 | AI77: =AI303 -> 11.746134 | AJ77: =AJ303 -> 11.104939 | AK77: =AJ77 -> 11.104939 | AL77: =AL303 -> 12.671504 | AM77: =AM303 -> 14.41218 | AN77: =AN303 -> 16.286925 | AO77: =AO303 -> 18.304311 | AP77: =AP303 -> 20.473408 | AQ77: =AQ303 -> 22.803814 | AR77: =AR303 -> 25.305679 | AS77: =AS303 -> 27.989741 | AT77: =AT303 -> 30.867355 | AU77: x
B78: Passivo Não Circulante | C78: =SUM(C79:C82) -> 64.983 | D78: =SUM(D79:D82) -> 82.171 | E78: =SUM(E79:E82) -> 77.419 | F78: =SUM(F79:F82) -> 55.2682 | G78: =F78 -> 55.2682 | H78: =SUM(H79:H82) -> 74.344 | I78: =SUM(I79:I82) -> 76.362 | J78: =SUM(J79:J82) -> 77.641 | K78: =SUM(K79:K82) -> 79.054 | L78: =K78 -> 79.054 | M78: =SUM(M79:M82) -> 81.266 | N78: =SUM(N79:N82) -> 82.791 | O78: =SUM(O79:O82) -> 84.688 | P78: =SUM(P79:P82) -> 85.095 | Q78: =P78 -> 85.095 | R78: =SUM(R79:R82) -> 83.495 | S78: =SUM(S79:S82) -> 89.93 | T78: =SUM(T79:T82) -> 90.227 | U78: =SUM(U79:U82) -> 90.745 | V78: =U78 -> 90.745 | W78: =SUM(W79:W82) -> 92.342 | X78: =SUM(X79:X82) -> 103.738 | Y78: =SUM(Y79:Y82) -> 106.351 | Z78: =SUM(Z79:Z82) -> 139.934 | AA78: =Z78 -> 139.934 | AB78: =SUM(AB79:AB82) -> 135.039 | AC78: =SUM(AC79:AC82) -> 133.859 | AD78: =SUM(AD79:AD82) -> 155.395 | AE78: =SUM(AE79:AE82) -> 158.09 | AF78: =AE78 -> 158.09 | AG78: =SUM(AG79:AG82) -> 165.118 | AH78: =SUM(AH79:AH82) -> 4.204 | AI78: =SUM(AI79:AI82) -> 4.204 | AJ78: =SUM(AJ79:AJ82) -> 4.204 | AK78: =AJ78 -> 4.204 | AL78: =SUM(AL79:AL82) -> 4.204 | AM78: =SUM(AM79:AM82) -> 4.204 | AN78: =SUM(AN79:AN82) -> 4.204 | AO78: =SUM(AO79:AO82) -> 4.204 | AP78: =SUM(AP79:AP82) -> 4.204 | AQ78: =SUM(AQ79:AQ82) -> 4.204 | AR78: =SUM(AR79:AR82) -> 4.204 | AS78: =SUM(AS79:AS82) -> 4.204 | AT78: =SUM(AT79:AT82) -> 4.204 | AU78: x
B79: Fornecedores | C79: 0 | D79: 0 | E79: 0 | F79: 0 | G79: =F79 -> 0 | H79: 0 | I79: 0 | J79: 0 | K79: 0 | L79: =K79 -> 0 | M79: 0 | N79: 1.927 | O79: 1.972 | P79: 1.586 | Q79: =P79 -> 1.586 | R79: 1.132 | S79: 0.879 | T79: 0.609 | U79: 0.294 | V79: =U79 -> 0.294 | W79: 0 | X79: 0 | Y79: 0 | Z79: 0 | AA79: =Z79 -> 0 | AB79: 0 | AC79: 0 | AD79: 0 | AE79: 0 | AF79: =AE79 -> 0 | AG79: 0 | AU79: x
B80: Dívida | C80: 0 | D80: 20.107 | E80: 14.542 | F80: 0 | G80: =F80 -> 0 | H80: 0 | I80: 0 | J80: 0 | K80: 0 | L80: =K80 -> 0 | M80: 0 | N80: 0 | O80: 0 | P80: 0 | Q80: =P80 -> 0 | R80: 0 | S80: 0 | T80: 0 | U80: 0 | V80: =U80 -> 0 | W80: 0 | X80: 0 | Y80: 0 | Z80: 0 | AA80: =Z80 -> 0 | AB80: 0 | AC80: 0 | AD80: 0 | AE80: 0 | AF80: =AE80 -> 0 | AG80: 0 | AU80: x
B81: Arrendamento | C81: 42.883 | D81: 40.605 | E81: 40.854 | F81: 44.0232 | G81: =F81 -> 44.0232 | H81: 63.602 | I81: 65.289 | J81: 66.699 | K81: 68.565 | L81: =K81 -> 68.565 | M81: 72.15 | N81: 71.907 | O81: 74.198 | P81: 75.6 | Q81: =P81 -> 75.6 | R81: 74.684 | S81: 81.617 | T81: 82.745 | U81: 84.245 | V81: =U81 -> 84.245 | W81: 86.713 | X81: 98.775 | Y81: 101.607 | Z81: 135.394 | AA81: =Z81 -> 135.394 | AB81: 130.699 | AC81: 129.697 | AD81: 151.518 | AE81: 153.919 | AF81: =AE81 -> 153.919 | AG81: 160.914 | AU81: x
B82: Provisão para riscos | C82: 22.1 | D82: 21.459 | E82: 22.023 | F82: 11.245 | G82: =F82 -> 11.245 | H82: 10.742 | I82: 11.073 | J82: 10.942 | K82: 10.489 | L82: =K82 -> 10.489 | M82: 9.116 | N82: 8.957 | O82: 8.518 | P82: 7.909 | Q82: =P82 -> 7.909 | R82: 7.679 | S82: 7.434 | T82: 6.873 | U82: 6.206 | V82: =U82 -> 6.206 | W82: 5.629 | X82: 4.963 | Y82: 4.744 | Z82: 4.54 | AA82: =Z82 -> 4.54 | AB82: 4.34 | AC82: 4.162 | AD82: 3.877 | AE82: 4.171 | AF82: =AE82 -> 4.171 | AG82: 4.204 | AH82: =AG82 -> 4.204 | AI82: =AH82 -> 4.204 | AJ82: =AI82 -> 4.204 | AK82: =AJ82 -> 4.204 | AL82: =AK82 -> 4.204 | AM82: =AL82 -> 4.204 | AN82: =AM82 -> 4.204 | AO82: =AN82 -> 4.204 | ... AT82: =AS82 -> 4.204 | AU82: x
B83: Patrimônio Líquido | C83: 11.823 | D83: 20.094 | E83: 27.261 | F83: 201.642 | G83: =F83 -> 201.642 | H83: 208.87 | I83: 222.248 | J83: 245.575 | K83: 267.807 | L83: =K83 -> 267.807 | M83: 287.781 | N83: 305.055 | O83: 317.938 | P83: 328.328 | Q83: =P83 -> 328.328 | R83: 348.237 | S83: 369.585 | T83: 390.905 | U83: 413.633 | V83: =U83 -> 413.633 | W83: 434.794 | X83: 448.046 | Y83: 453.573 | Z83: 472.809 | AA83: =Z83 -> 472.809 | AB83: 484.021 | AC83: 512.231 | AD83: 531.619 | AE83: 566.935 | AF83: =AE83 -> 566.935 | AG83: 591.469 | AH83: =SUM(AH84:AH85) -> 606.6508 | AI83: =SUM(AI84:AI85) -> 615.5805 | AJ83: =SUM(AJ84:AJ85) -> 677.9841 | AK83: =AJ83 -> 677.9841 | AL83: =SUM(AL84:AL85) -> 783.79967 | AM83: =SUM(AM84:AM85) -> 899.3108 | AN83: =SUM(AN84:AN85) -> 1022.9341 | AO83: =SUM(AO84:AO85) -> 1155.3421 | AP83: =SUM(AP84:AP85) -> 1297.2168 | AQ83: =SUM(AQ84:AQ85) -> 1449.2566 | AR83: =SUM(AR84:AR85) -> 1612.1815 | AS83: =SUM(AS84:AS85) -> 1786.7388 | AT83: =SUM(AT84:AT85) -> 1973.7069 | AU83: x
B84: Controladores | C84: =(C83-C85) -> 11.823 | D84: =(D83-D85) -> 20.094 | E84: =(E83-E85) -> 27.261 | F84: =(F83-F85) -> 201.642 | G84: =F84 -> 201.642 | H84: =(H83-H85) -> 208.87 | I84: =(I83-I85) -> 222.248 | J84: =(J83-J85) -> 245.575 | K84: =(K83-K85) -> 267.807 | L84: =K84 -> 267.807 | M84: =(M83-M85) -> 287.781 | N84: =(N83-N85) -> 305.055 | O84: =(O83-O85) -> 317.938 | P84: =(P83-P85) -> 328.328 | Q84: =P84 -> 328.328 | R84: =(R83-R85) -> 348.237 | S84: =(S83-S85) -> 369.585 | T84: =(T83-T85) -> 390.905 | U84: =(U83-U85) -> 413.633 | V84: =U84 -> 413.633 | W84: =(W83-W85) -> 434.794 | X84: =(X83-X85) -> 448.046 | Y84: =(Y83-Y85) -> 453.573 | Z84: =(Z83-Z85) -> 472.809 | AA84: =Z84 -> 472.809 | AB84: =(AB83-AB85) -> 484.021 | AC84: =(AC83-AC85) -> 510.935 | AD84: =(AD83-AD85) -> 530.276 | AE84: =(AE83-AE85) -> 564.029 | AF84: =AE84 -> 564.029 | AG84: =(AG83-AG85) -> 588.427 | AH84: =AG84+AH46+AH101 -> 603.6088 | AI84: =AH84+AI46+AI101 -> 612.5385 | AJ84: =AI84+AJ46+AJ101 -> 674.9421 | AK84: =AJ84 -> 674.9421 | AL84: =AK84+AL46+AL101 -> 780.75767 | AM84: =AL84+AM46+AM101 -> 896.2688 | AN84: =AM84+AN46+AN101 -> 1019.8921 | AO84: =AN84+AO46+AO101 -> 1152.3001 | AP84: =AO84+AP46+AP101 -> 1294.1748 | AQ84: =AP84+AQ46+AQ101 -> 1446.2146 | AR84: =AQ84+AR46+AR101 -> 1609.1395 | AS84: =AR84+AS46+AS101 -> 1783.6968 | AT84: =AS84+AT46+AT101 -> 1970.6649 | AU84: x
B85: Não Controladores | C85: 0 | D85: 0 | E85: 0 | F85: 0 | G85: =F85 -> 0 | H85: 0 | I85: 0 | J85: 0 | K85: 0 | L85: =K85 -> 0 | M85: 0 | N85: 0 | O85: 0 | P85: 0 | Q85: =P85 -> 0 | R85: 0 | S85: 0 | T85: 0 | U85: 0 | V85: =U85 -> 0 | W85: 0 | X85: 0 | Y85: 0 | Z85: 0 | AA85: =Z85 -> 0 | AB85: 0 | AC85: 1.296 | AD85: 1.343 | AE85: 2.906 | AF85: =AE85 -> 2.906 | AG85: 3.042 | AH85: =AG85 -> 3.042 | AI85: =AH85 -> 3.042 | AJ85: =AI85 -> 3.042 | AK85: =AJ85 -> 3.042 | AL85: =AK85 -> 3.042 | AM85: =AL85 -> 3.042 | AN85: =AM85 -> 3.042 | AO85: =AN85 -> 3.042 | ... AT85: =AS85 -> 3.042 | AU85: x
AU86: x
B87: Check BP | C87: =IF(ABS(C52-C68)>0.1,"Erro","Ok") -> Ok | D87: =IF(ABS(D52-D68)>0.1,"Erro","Ok") -> Ok | E87: =IF(ABS(E52-E68)>0.1,"Erro","Ok") -> Ok | F87: =IF(ABS(F52-F68)>0.1,"Erro","Ok") -> Ok | G87: =IF(ABS(G52-G68)>0.1,"Erro","Ok") -> Ok | H87: =IF(ABS(H52-H68)>0.1,"Erro","Ok") -> Ok | I87: =IF(ABS(I52-I68)>0.1,"Erro","Ok") -> Ok | J87: =IF(ABS(J52-J68)>0.1,"Erro","Ok") -> Ok | ... AT87: =IF(ABS(AT52-AT68)>0.1,"Erro","Ok") -> Ok | AU87: x
AU88: x
A89: * | B89: 4 - Cash Flow | AU89: x
AU90: x
B91: EBITDA | D91: =D30 -> 1.065 | E91: =E30 -> 12.918 | F91: =F30 -> 33.350691 | G91: =SUM(C91:F91) -> 47.333691 | H91: =H30 -> 10.99 | I91: =I30 -> 20.156045 | J91: =J30 -> 27.033328 | K91: =K30 -> 43.698564 | L91: =SUM(H91:K91) -> 101.87794 | M91: =M30 -> 32.371795 | N91: =N30 -> 28.794748 | O91: =O30 -> 34.239047 | P91: =P30 -> 48.355522 | Q91: =SUM(M91:P91) -> 143.76111 | R91: =R30 -> 37.778682 | S91: =S30 -> 40.870661 | T91: =T30 -> 41.280373 | U91: =U30 -> 53.800624 | V91: =SUM(R91:U91) -> 173.73034 | W91: =W30 -> 41.41331 | X91: =X30 -> 43.841 | Y91: =Y30 -> 45.007061 | Z91: =Z30 -> 65.964073 | AA91: =SUM(W91:Z91) -> 196.22544 | AB91: =AB30 -> 58.586613 | AC91: =AC30 -> 58.298 | AD91: =AD30 -> 56.872656 | AE91: =AE30 -> 75.656 | AF91: =SUM(AB91:AE91) -> 249.41327 | AG91: =AG30 -> 63.79 | AH91: =AH30 -> 66.826231 | AI91: =AI30 -> 71.24605 | AJ91: =AJ30 -> 96.079555 | AK91: =SUM(AG91:AJ91) -> 297.94183 | AL91: =AL30 -> 353.14299 | AM91: =AM30 -> 416.63398 | AN91: =AN30 -> 487.75857 | AO91: =AO30 -> 567.20042 | AP91: =AP30 -> 655.69482 | AQ91: =AQ30 -> 754.03214 | AR91: =AR30 -> 863.06161 | AS91: =AS30 -> 983.69522 | AT91: =AT30 -> 1116.912 | AU91: x
B92: (-) Resultado financeiro | D92: =D38 -> -0.9 | E92: =E38 -> -0.717 | F92: =F38 -> -2.3635138 | G92: =SUM(C92:F92) -> -3.9805138 | H92: =H38 -> 0.011 | I92: =I38 -> -1.077 | J92: =J38 -> -0.84942961 | K92: =K38 -> 0.27859706 | L92: =SUM(H92:K92) -> -1.6368326 | M92: =M38 -> -1.2259987 | N92: =N38 -> -0.798 | O92: =O38 -> -1.1429935 | P92: =P38 -> -1.6297332 | Q92: =SUM(M92:P92) -> -4.7967253 | R92: =R38 -> -2.66 | S92: =S38 -> -2.881 | T92: =T38 -> -3.051 | U92: =U38 -> -3.1921326 | V92: =SUM(R92:U92) -> -11.784133 | W92: =W38 -> -3.534 | X92: =X38 -> -3.937 | Y92: =Y38 -> -5.329 | Z92: =Z38 -> -3.965731 | AA92: =SUM(W92:Z92) -> -16.765731 | AB92: =AB38 -> -7.685 | AC92: =AC38 -> -6.945 | AD92: =AD38 -> -8.5344265 | AE92: =AE38 -> -9.512 | AF92: =SUM(AB92:AE92) -> -32.676427 | AG92: =AG38 -> -10.438 | AH92: =AH38 -> -8.6196586 | AI92: =AI38 -> -9.2383245 | AJ92: =AJ38 -> -11.465266 | AK92: =SUM(AG92:AJ92) -> -39.761249 | AL92: =AL38 -> -46.131487 | AM92: =AM38 -> -52.682328 | AN92: =AN38 -> -57.280853 | AO92: =AO38 -> -61.873279 | AP92: =AP38 -> -66.429598 | AQ92: =AQ38 -> -70.915934 | AR92: =AR38 -> -75.294189 | AS92: =AS38 -> -79.521653 | AT92: =AT38 -> -83.550594 | AU92: x
B93: (-) IR/CS | D93: =D43 -> 1.284 | E93: =E43 -> -2.543 | F93: =F43 -> -7.4551602 | G93: =SUM(C93:F93) -> -8.7141602 | H93: =H43 -> -1.333 | I93: =I43 -> -3.271 | J93: =J43 -> -1.3892769 | K93: =K43 -> -5.5921098 | L93: =SUM(H93:K93) -> -11.585387 | M93: =M43 -> -7.1686303 | N93: =N43 -> -6.419 | O93: =O43 -> -3.9200337 | P93: =P43 -> -6.453 | Q93: =SUM(M93:P93) -> -23.960664 | R93: =R43 -> -4.2142218 | S93: =S43 -> -4.966 | T93: =T43 -> -4.691 | U93: =U43 -> -8.648 | V93: =SUM(R93:U93) -> -22.519222 | W93: =W43 -> -4.396 | X93: =X43 -> -5.723 | Y93: =Y43 -> -6.899678 | Z93: =Z43 -> -12.668 | AA93: =SUM(W93:Z93) -> -29.686678 | AB93: =AB43 -> -7.845 | AC93: =AC43 -> -8.163 | AD93: =AD43 -> -9.016 | AE93: =AE43 -> -12.436 | AF93: =SUM(AB93:AE93) -> -37.46 | AG93: =AG43 -> -9.001 | AH93: =AH43 -> -13.322946 | AI93: =AI43 -> -3.4036637 | AJ93: =AJ43 -> -9.848502 | AK93: =SUM(AG93:AJ93) -> -35.576112 | AL93: =AL43 -> -51.966339 | AM93: =AM43 -> -36.359147 | AN93: =AN43 -> -44.856219 | AO93: =AO43 -> -54.910463 | AP93: =AP43 -> -66.86585 | AQ93: =AQ43 -> -80.898469 | AR93: =AR43 -> -97.203272 | AS93: =AS43 -> -115.99451 | AT93: =AT43 -> -137.50643 | AU93: x
B94: (-) ∆ WKC | D94: =-(D287-C287) -> -17.993 | E94: =-(E287-D287) -> -18.775 | F94: =-(F287-E287) -> -40.5478 | G94: =SUM(C94:F94) -> -77.3158 | H94: =-(H287-F287) -> 5.0692666 | I94: =-(I287-H287) -> -33.928355 | J94: =-(J287-I287) -> -27.925595 | K94: =-(K287-J287) -> -31.548004 | L94: =SUM(H94:K94) -> -88.332687 | M94: =-(M287-K287) -> -1.1361527 | N94: =-(N287-M287) -> -10.357274 | O94: =-(O287-N287) -> -23.271285 | P94: =-(P287-O287) -> -25.339296 | Q94: =SUM(M94:P94) -> -60.104009 | R94: =-(R287-P287) -> 5.1485153 | S94: =-(S287-R287) -> -22.142154 | T94: =-(T287-S287) -> -16.448925 | U94: =-(U287-T287) -> -34.867162 | V94: =SUM(R94:U94) -> -68.309725 | W94: =-(W287-U287) -> 28.812796 | X94: =-(X287-W287) -> -4.1190898 | Y94: =-(Y287-X287) -> -23.900408 | Z94: =-(Z287-Y287) -> -71.655647 | AA94: =SUM(W94:Z94) -> -70.862348 | AB94: =-(AB287-Z287) -> 30.687184 | AC94: =-(AC287-AB287) -> -22.554337 | AD94: =-(AD287-AC287) -> -25.779277 | AE94: =-(AE287-AD287) -> -55.955553 | AF94: =SUM(AB94:AE94) -> -73.601983 | AG94: =-(AG287-AE287) -> 18.401873 | AH94: =-(AH287-AG287) -> -8.097126 | AI94: =-(AI287-AH287) -> -1.5650872 | AJ94: =-(AJ287-AI287) -> -57.29136 | AK94: =SUM(AG94:AJ94) -> -48.5517 | AL94: =-(AL287-AK287) -> -73.381562 | AM94: =-(AM287-AL287) -> -81.537316 | AN94: =-(AN287-AM287) -> -87.817429 | AO94: =-(AO287-AN287) -> -94.499064 | AP94: =-(AP287-AO287) -> -101.60558 | AQ94: =-(AQ287-AP287) -> -109.16162 | AR94: =-(AR287-AQ287) -> -117.1932 | AS94: =-(AS287-AR287) -> -125.72772 | AT94: =-(AT287-AS287) -> -134.79413 | AU94: x
B95: (-) Adição Imobilizado | D95: =-D374 -> 0 | E95: =-E374 -> -0.262 | F95: =-F374 -> -9.055 | G95: =SUM(C95:F95) -> -9.317 | H95: =-H374 -> -0.121 | I95: =-I374 -> -3.479 | J95: =-J374 -> -2.535 | K95: =-K374 -> -3.684 | L95: =SUM(H95:K95) -> -9.819 | M95: =-M374 -> -3.599 | N95: =-N374 -> -20.796 | O95: =-O374 -> -17.552 | P95: =-P374 -> -6.645 | Q95: =SUM(M95:P95) -> -48.592 | R95: =-R374 -> -4.341 | S95: =-S374 -> -5.223 | T95: =-T374 -> -4.155 | U95: =-U374 -> -6.362 | V95: =SUM(R95:U95) -> -20.081 | W95: =-W374 -> -6.297 | X95: =-X374 -> -8.49 | Y95: =-Y374 -> -9.396 | Z95: =-Z374 -> -11.08 | AA95: =SUM(W95:Z95) -> -35.263 | AB95: =-AB374 -> -6.129 | AC95: =-AC374 -> -6.198 | AD95: =-AD374 -> -5.788 | AE95: =-AE374 -> -11.359 | AF95: =SUM(AB95:AE95) -> -29.474 | AG95: =-AG374 -> -7.557 | AH95: =-AH374 -> -10.239527 | AI95: =-AI374 -> -10.677344 | AJ95: =-AJ374 -> -13.455771 | AK95: =SUM(AG95:AJ95) -> -41.929642 | AL95: =-AL374 -> -47.188925 | AM95: =-AM374 -> -53.010723 | AN95: =-AN374 -> -59.27071 | AO95: =-AO374 -> -65.996638 | AP95: =-AP374 -> -73.217866 | AQ95: =-AQ374 -> -80.965449 | AR95: =-AR374 -> -89.272229 | AS95: =-AS374 -> -98.172934 | AT95: =-AT374 -> -107.70428 | AU95: x
B96: (-) Adição Intangível | D96: =-D391 -> -0.028 | E96: =-E391 -> -0.032 | F96: =-F391 -> -0.148 | G96: =SUM(C96:F96) -> -0.208 | H96: =-H391 -> -0.425 | I96: =-I391 -> -0.791 | J96: =-J391 -> -1.307 | K96: =-K391 -> -1.318 | L96: =SUM(H96:K96) -> -3.841 | M96: =-M391 -> -1.342 | N96: =-N391 -> -1.338 | O96: =-O391 -> -3.022 | P96: =-P391 -> -2.247 | Q96: =SUM(M96:P96) -> -7.949 | R96: =-R391 -> -2.9 | S96: =-S391 -> -2.53 | T96: =-T391 -> -6.227 | U96: =-U391 -> -1.975 | V96: =SUM(R96:U96) -> -13.632 | W96: =-W391 -> -5.008 | X96: =-X391 -> -1.468 | Y96: =-Y391 -> -2.919 | Z96: =-Z391 -> -0.523 | AA96: =SUM(W96:Z96) -> -9.918 | AB96: =-AB391 -> -2.795 | AC96: =-AC391 -> -5.584 | AD96: =-AD391 -> -4.042 | AE96: =-AE391 -> -4.212 | AF96: =SUM(AB96:AE96) -> -16.633 | AG96: =-AG391 -> -3.97 | AH96: =-AH391 -> -2.6054783 | AI96: =-AI391 -> -2.7509875 | AJ96: =-AJ391 -> -3.6744015 | AK96: =SUM(AG96:AJ96) -> -13.000867 | AL96: =-AL391 -> -14.834889 | AM96: =-AM391 -> -16.872748 | AN96: =-AN391 -> -19.067565 | AO96: =-AO391 -> -21.429376 | AP96: =-AP391 -> -23.9688 | AQ96: =-AQ391 -> -26.697072 | AR96: =-AR391 -> -29.626076 | AS96: =-AS391 -> -32.768383 | AT96: =-AT391 -> -36.137287 | AU96: x
B97: (-) Depreciação Direito de Uso | D97: =D363 -> -2.003 | E97: =E363 -> -2.023 | F97: =F363 -> -1.859 | G97: =SUM(C97:F97) -> -5.885 | H97: =H363 -> -1.707 | I97: =I363 -> -1.795 | J97: =J363 -> -2.555 | K97: =K363 -> -2.414 | L97: =SUM(H97:K97) -> -8.471 | M97: =M363 -> -2.824 | N97: =N363 -> -3.071 | O97: =O363 -> -3.219 | P97: =P363 -> -3.701 | Q97: =SUM(M97:P97) -> -12.815 | R97: =R363 -> -3.857 | S97: =S363 -> -3.989 | T97: =T363 -> -4.232 | U97: =U363 -> -4.295 | V97: =SUM(R97:U97) -> -16.373 | W97: =W363 -> -4.262 | X97: =X363 -> -4.316 | Y97: =Y363 -> -4.47 | Z97: =Z363 -> -4.57 | AA97: =SUM(W97:Z97) -> -17.618 | AB97: =AB363 -> -4.696 | AC97: =AC363 -> -5.021 | AD97: =AD363 -> -4.862 | AE97: =AE363 -> -5.127 | AF97: =SUM(AB97:AE97) -> -19.706 | AG97: =AG363 -> -5.276 | AH97: =AH363 -> -5.4948029 | AI97: =AI363 -> -5.4948029 | AJ97: =AJ363 -> -5.9810681 | AK97: =SUM(AG97:AJ97) -> -22.246674 | AL97: =AL363 -> -25.861758 | AM97: =AM363 -> -29.782735 | AN97: =AN363 -> -34.031154 | AO97: =AO363 -> -38.629959 | AP97: =AP363 -> -43.603566 | AQ97: =AQ363 -> -48.977959 | AR97: =AR363 -> -54.780782 | AS97: =AS363 -> -61.041443 | AT97: =AT363 -> -67.791218 | AU97: x
AU98: x
B99: Fluxo de Caixa Operacional | D99: =SUM(D91:D97) -> -18.575 | E99: =SUM(E91:E97) -> -11.434 | F99: =SUM(F91:F97) -> -28.077783 | G99: =SUM(C99:F99) -> -58.086783 | H99: =SUM(H91:H97) -> 12.484267 | I99: =SUM(I91:I97) -> -24.18531 | J99: =SUM(J91:J97) -> -9.5279731 | K99: =SUM(K91:K97) -> -0.5789528 | L99: =SUM(H99:K99) -> -21.807969 | M99: =SUM(M91:M97) -> 15.076014 | N99: =SUM(N91:N97) -> -13.984526 | O99: =SUM(O91:O97) -> -17.888265 | P99: =SUM(P91:P97) -> 2.3404922 | Q99: =SUM(M99:P99) -> -14.456285 | R99: =SUM(R91:R97) -> 24.954975 | S99: =SUM(S91:S97) -> -0.86049224 | T99: =SUM(T91:T97) -> 2.4754485 | U99: =SUM(U91:U97) -> -5.5386707 | V99: =SUM(R99:U99) -> 21.031261 | W99: =SUM(W91:W97) -> 46.729105 | X99: =SUM(X91:X97) -> 15.78791 | Y99: =SUM(Y91:Y97) -> -7.9070247 | Z99: =SUM(Z91:Z97) -> -38.498304 | AA99: =SUM(W99:Z99) -> 16.111687 | AB99: =SUM(AB91:AB97) -> 60.123797 | AC99: =SUM(AC91:AC97) -> 3.832663 | AD99: =SUM(AD91:AD97) -> -1.1490484 | AE99: =SUM(AE91:AE97) -> -22.945553 | AF99: =SUM(AB99:AE99) -> 39.861858 | AG99: =SUM(AG91:AG97) -> 45.949873 | AH99: =SUM(AH91:AH97) -> 18.446692 | AI99: =SUM(AI91:AI97) -> 38.11584 | AJ99: =SUM(AJ91:AJ97) -> -5.6368137 | AK99: =SUM(AG99:AJ99) -> 96.875591 | AL99: =SUM(AL91:AL97) -> 93.778026 | AM99: =SUM(AM91:AM97) -> 146.38899 | AN99: =SUM(AN91:AN97) -> 185.43464 | AO99: =SUM(AO91:AO97) -> 229.86164 | AP99: =SUM(AP91:AP97) -> 280.00356 | AQ99: =SUM(AQ91:AQ97) -> 336.41563 | AR99: =SUM(AR91:AR97) -> 399.69186 | AS99: =SUM(AS91:AS97) -> 470.46858 | AT99: =SUM(AT91:AT97) -> 549.42803 | AU99: x
AU100: x
B101: (-) Dividendos | D101: =-D152 -> -0.231 | E101: =-E152 -> 0 | F101: =-F152 -> -114.064 | G101: =SUM(C101:F101) -> -114.295 | H101: =-H152 -> 0 | I101: =-I152 -> -6.135 | J101: =-J152 -> 0 | K101: =-K152 -> -9.53 | L101: =SUM(H101:K101) -> -15.665 | M101: =-M152 -> 0 | N101: =-N152 -> -9.881 | O101: =-O152 -> 0 | P101: =-P152 -> -12.256 | Q101: =SUM(M101:P101) -> -22.137 | R101: =-R152 -> -0.15273964 | S101: =-S152 -> -24.36 | T101: =-T152 -> -0.662 | U101: =-U152 -> -0.698 | V101: =SUM(R101:U101) -> -25.87274 | W101: =-W152 -> -0.99 | X101: =-X152 -> -33.781091 | Y101: =-Y152 -> -13.019909 | Z101: =-Z152 -> -10.898 | AA101: =SUM(W101:Z101) -> -58.689 | AB101: =-AB152 -> -16.131 | AC101: =-AC152 -> -29.942 | AD101: =-AD152 -> -1.17 | AE101: =-AE152 -> -1.231 | AF101: =SUM(AB101:AE101) -> -48.474 | AG101: =-AG152 -> -2.937 | AH101: =-AH152 -> -18.446692 | AI101: =-AI152 -> -38.11584 | AJ101: =-AJ152 -> 0 | AK101: =SUM(AG101:AJ101) -> -59.499531 | AL101: =-AL152 -> -93.778026 | AM101: =-AM152 -> -146.38899 | AN101: =-AN152 -> -185.43464 | AO101: =-AO152 -> -229.86164 | AP101: =-AP152 -> -280.00356 | AQ101: =-AQ152 -> -336.41563 | AR101: =-AR152 -> -399.69186 | AS101: =-AS152 -> -470.46858 | AT101: =-AT152 -> -549.42803 | AU101: x
...
